[
  {
    "step_id": 0,
    "step_type": "action",
    "reasoning": "Initial observation suggests a relationship between voltage, current, and resistance. Increasing the current will help us determine if Ohm's Law holds true (V = IR).",
    "parsed_action": {
      "action_type": "increase",
      "variable": "current"
    },
    "final_equation": null,
    "done": false
  },
  {
    "step_id": 1,
    "step_type": "finish",
    "reasoning": "The increase in current from 2.0A to 3.0A resulted in a proportional increase in voltage from 20V to 30V. This supports Ohm's Law (V = IR). No need to further increase current as we already have enough evidence.",
    "parsed_action": null,
    "final_equation": "voltage = current * resistance",
    "done": true
  }
]