[
  {
    "step_id": 0,
    "step_type": "action",
    "reasoning": "Initial observation shows d1=10, d2=20, d3=30 and total_distance=60. Summing these (10+20+30) equals 60, suggesting total_distance = d1 + d2 + d3. I will verify this by increasing d1 and checking if total_distance increases by the same amount.",
    "parsed_action": {
      "action_type": "increase",
      "variable": "d1"
    },
    "final_equation": null,
    "done": false
  },
  {
    "step_id": 1,
    "step_type": "action",
    "reasoning": "Initial observation shows d1=10, d2=20, d3=30 and total_distance=60. Summing these (10+20+30) equals 60, suggesting total_distance = d1 + d2 + d3. I will verify this by increasing d1 and checking if total_distance increases by the same amount.",
    "parsed_action": {
      "action_type": "increase",
      "variable": "d1"
    },
    "final_equation": null,
    "done": false
  },
  {
    "step_id": 2,
    "step_type": "action",
    "reasoning": "Current state shows d1=30, d2=20, d3=30, total_distance=80. The sum 30+20+30 equals 80, consistent with total_distance = d1 + d2 + d3. I will verify by decreasing d1 and checking if total_distance decreases by the same amount.",
    "parsed_action": {
      "action_type": "decrease",
      "variable": "d1"
    },
    "final_equation": null,
    "done": false
  },
  {
    "step_id": 3,
    "step_type": "action",
    "reasoning": "Current state shows d1=20, d2=20, d3=30, total_distance=70. The sum 20+20+30 equals 70, consistent with total_distance = d1 + d2 + d3. I will verify by changing d2 and checking if total_distance changes accordingly.",
    "parsed_action": {
      "action_type": "increase",
      "variable": "d2"
    },
    "final_equation": null,
    "done": false
  },
  {
    "step_id": 4,
    "step_type": "action",
    "reasoning": "Current state shows d1=20, d2=30, d3=30, total_distance=80. The sum 20+30+30 equals 80, consistent with total_distance = d1 + d2 + d3. I will verify by changing d3 and checking if total_distance changes accordingly.",
    "parsed_action": {
      "action_type": "increase",
      "variable": "d3"
    },
    "final_equation": null,
    "done": false
  },
  {
    "step_id": 5,
    "step_type": "finish",
    "reasoning": "Current state shows d1=20, d2=30, d3=40, total_distance=90. The sum 20+30+40 equals 90, consistent with total_distance = d1 + d2 + d3. All previous steps also supported this linear relationship. I have gathered sufficient evidence to conclude the equation.",
    "parsed_action": null,
    "final_equation": "total_distance = d1 + d2 + d3",
    "done": true
  }
]