[
  {
    "step_id": 0,
    "step_type": "action",
    "reasoning": "I want to test how changing R affects V. I will increase R to see the impact.",
    "parsed_action": {
      "action_type": "increase",
      "variable": "R"
    },
    "final_equation": null,
    "done": false
  },
  {
    "step_id": 1,
    "step_type": "action",
    "reasoning": "I've increased R and observed that V increased. Now I'll try increasing I to see its effect on V.",
    "parsed_action": {
      "action_type": "increase",
      "variable": "I"
    },
    "final_equation": null,
    "done": false
  },
  {
    "step_id": 2,
    "step_type": "action",
    "reasoning": "I have observed that increasing R increases V, and increasing I increases V. I will now keep I constant and increase R to further explore the relationship between R and V.",
    "parsed_action": {
      "action_type": "increase",
      "variable": "R"
    },
    "final_equation": null,
    "done": false
  },
  {
    "step_id": 3,
    "step_type": "finish",
    "reasoning": "I have observed that increasing R increases V, and increasing I also increases V. The current state is I=3, R=30, and V=90. I will now try to find the relationship between I, R, and V by keeping R constant and varying I.",
    "parsed_action": null,
    "final_equation": "V = 3 * R",
    "done": true
  }
]