[
  {
    "step_id": 0,
    "step_type": "action",
    "reasoning": "Initial observation shows Y = 20.0, A = 2.0 and B = 10.0. Since Y is dependent on both A and B, we will first manipulate A and observe the change in Y.",
    "parsed_action": {
      "action_type": "increase",
      "variable": "A"
    },
    "final_equation": null,
    "done": false
  },
  {
    "step_id": 1,
    "step_type": "action",
    "reasoning": "Y remains constant when B is kept constant and A is increased. Let's now decrease A to further investigate the relationship between Y and A.",
    "parsed_action": {
      "action_type": "decrease",
      "variable": "A"
    },
    "final_equation": null,
    "done": false
  },
  {
    "step_id": 2,
    "step_type": "action",
    "reasoning": "Y remains constant when A is decreased to its original value, which suggests a linear relationship between Y and A. Let's keep A constant and manipulate B to see if Y is also linearly dependent on B.",
    "parsed_action": {
      "action_type": "decrease",
      "variable": "B"
    },
    "final_equation": null,
    "done": false
  },
  {
    "step_id": 3,
    "step_type": "action",
    "reasoning": "Y is linearly dependent on A and does not seem to have a relationship with B at the current range of values. Let's increase A again to confirm the linear relationship and find the slope.",
    "parsed_action": {
      "action_type": "increase",
      "variable": "A"
    },
    "final_equation": null,
    "done": false
  },
  {
    "step_id": 4,
    "step_type": "action",
    "reasoning": "Y is linearly dependent on A and does not seem to have a relationship with B at the current range of values. Let's increase A further to find the slope and intercept.",
    "parsed_action": {
      "action_type": "increase",
      "variable": "A"
    },
    "final_equation": null,
    "done": false
  },
  {
    "step_id": 5,
    "step_type": "action",
    "reasoning": "Increasing A further to confirm the linear relationship and find the slope and intercept",
    "parsed_action": {
      "action_type": "increase",
      "variable": "A"
    },
    "final_equation": null,
    "done": false
  }
]