{"redundancy_penalty":0,"equation_correct":1,"_runtime":312,"mean_variable_isolation_score":0.9722233333333333,"n_runs":30,"state_coverage_ratio":0.6667,"parse_error_rate":0.03333333333333333,"_step":29,"_wandb":{"runtime":312},"episodes":{"_latest_artifact_path":"wandb-client-artifact://we0f4ox88u7j6t32zs5hcqkl7kpepj3iyje4l4m1m1g07mpt6r1zi0a31mdks5plqacz5orjpq3qyb5o3tmoatf7sq2hb9j9jpdf9uup5a120qkp9i97g2xe76dv5ker:latest/episodes.table.json","size":3590,"artifact_path":"wandb-client-artifact://wq3fx6keu5pzs2zf8umorhidqzmb8ss7k52yum62a3zw2gu6m1a5o9kfa1ants6u046e3a7qxb8cunz8jixvfvjsitjh3e3xj5h3u9nd4bb0qe50fsj99v7nlduy73p7/episodes.table.json","log_mode":"IMMUTABLE","nrows":30,"sha256":"6c6a20283a5a87b43dca84035e9f8a7b5cddc80e7a368b6dc91918ba2d621def","ncols":13,"_type":"table-file","path":"media/table/episodes_29_6c6a20283a5a87b43dca.table.json"},"finish_rate":0.9666666666666667,"finish_called":1,"mean_state_coverage_ratio":0.68113,"variable_isolation_score":1,"discovery_efficiency":0.333333,"mean_redundancy_penalty":0.03166666666666667,"success":1,"_timestamp":1.7774659261576293e+09,"mean_total_steps":3.466666666666667,"success_rate":0.9,"termination_breakdown":{"finish_success":27,"finish_wrong":2,"max_steps":0,"parse_error":1},"mean_steps_to_success":3.4444444444444446,"mean_discovery_efficiency":0.2688887,"steps_to_success":3,"total_steps":3}