[
  {
    "step_id": 0,
    "step_type": "action",
    "reasoning": "Start exploration, increase time to observe how position changes over time.",
    "parsed_action": {
      "action_type": "increase",
      "variable": "time"
    },
    "final_equation": null,
    "done": false
  },
  {
    "step_id": 1,
    "step_type": "action",
    "reasoning": "Start exploration, increase time to observe how position changes over time.",
    "parsed_action": {
      "action_type": "increase",
      "variable": "time"
    },
    "final_equation": null,
    "done": false
  },
  {
    "step_id": 2,
    "step_type": "action",
    "reasoning": "Observe the effect of changing initial position on position.",
    "parsed_action": {
      "action_type": "increase",
      "variable": "initial_position"
    },
    "final_equation": null,
    "done": false
  },
  {
    "step_id": 3,
    "step_type": "action",
    "reasoning": "Observe the effect of changing velocity on position.",
    "parsed_action": {
      "action_type": "increase",
      "variable": "velocity"
    },
    "final_equation": null,
    "done": false
  },
  {
    "step_id": 4,
    "step_type": "action",
    "reasoning": "Observe the effect of changing time on position with initial position and velocity constant.",
    "parsed_action": {
      "action_type": "decrease time",
      "variable": "time"
    },
    "final_equation": null,
    "done": false
  },
  {
    "step_id": 5,
    "step_type": "action",
    "reasoning": "Observe the effect of changing time on position with initial position and velocity constant.",
    "parsed_action": {
      "action_type": "increase time",
      "variable": "time"
    },
    "final_equation": null,
    "done": false
  },
  {
    "step_id": 6,
    "step_type": "action",
    "reasoning": "Increase time to observe the effect of velocity on position",
    "parsed_action": {
      "action_type": "increase",
      "variable": "time"
    },
    "final_equation": null,
    "done": false
  },
  {
    "step_id": 7,
    "step_type": "action",
    "reasoning": "Observe the effect of changing velocity on position with time constant.",
    "parsed_action": {
      "action_type": "decrease velocity",
      "variable": "velocity"
    },
    "final_equation": null,
    "done": false
  },
  {
    "step_id": 8,
    "step_type": "action",
    "reasoning": "Observe the effect of changing time on position with initial position constant.",
    "parsed_action": {
      "action_type": "increase",
      "variable": "time"
    },
    "final_equation": null,
    "done": false
  },
  {
    "step_id": 9,
    "step_type": "action",
    "reasoning": "Observe the effect of changing velocity on position with time constant.",
    "parsed_action": {
      "action_type": "increase velocity",
      "variable": "velocity"
    },
    "final_equation": null,
    "done": false
  },
  {
    "step_id": 10,
    "step_type": "action",
    "reasoning": "Observe the effect of changing time on position with initial position and velocity constant.",
    "parsed_action": {
      "action_type": "increase time",
      "variable": "time"
    },
    "final_equation": null,
    "done": false
  },
  {
    "step_id": 11,
    "step_type": "action",
    "reasoning": "Increase time to observe the effect of velocity on position.",
    "parsed_action": {
      "action_type": "increase",
      "variable": "time"
    },
    "final_equation": null,
    "done": false
  },
  {
    "step_id": 12,
    "step_type": "action",
    "reasoning": "Observe the effect of changing time on position with initial position constant and velocity constant.",
    "parsed_action": {
      "action_type": "increase time",
      "variable": "time"
    },
    "final_equation": null,
    "done": false
  },
  {
    "step_id": 13,
    "step_type": "action",
    "reasoning": "Observe the effect of changing initial position on position, then change velocity to see if position changes.",
    "parsed_action": {
      "action_type": "increase initial_position",
      "variable": "initial_position"
    },
    "final_equation": null,
    "done": false
  },
  {
    "step_id": 14,
    "step_type": "action",
    "reasoning": "Observe the effect of changing initial position on position.",
    "parsed_action": {
      "action_type": "increase initial_position",
      "variable": "initial_position"
    },
    "final_equation": null,
    "done": false
  },
  {
    "step_id": 15,
    "step_type": "action",
    "reasoning": "Observe the effect of changing time on position with initial position and velocity constant.",
    "parsed_action": {
      "action_type": "increase time",
      "variable": "time"
    },
    "final_equation": null,
    "done": false
  },
  {
    "step_id": 16,
    "step_type": "action",
    "reasoning": "Observe the effect of changing initial position on position, then change time to see if position changes.",
    "parsed_action": {
      "action_type": "increase initial_position",
      "variable": "initial_position"
    },
    "final_equation": null,
    "done": false
  },
  {
    "step_id": 17,
    "step_type": "action",
    "reasoning": "Observe the effect of changing velocity on position with time constant.",
    "parsed_action": {
      "action_type": "increase velocity",
      "variable": "velocity"
    },
    "final_equation": null,
    "done": false
  },
  {
    "step_id": 18,
    "step_type": "action",
    "reasoning": "Observe the effect of changing time on position with initial position and velocity constant.",
    "parsed_action": {
      "action_type": "increase time",
      "variable": "time"
    },
    "final_equation": null,
    "done": false
  },
  {
    "step_id": 19,
    "step_type": "action",
    "reasoning": "Observe the effect of changing time on position with initial position and velocity constant.",
    "parsed_action": {
      "action_type": "increase time",
      "variable": "time"
    },
    "final_equation": null,
    "done": false
  },
  {
    "step_id": 20,
    "step_type": "action",
    "reasoning": "Observe the effect of changing velocity on position with time constant.",
    "parsed_action": {
      "action_type": "increase velocity",
      "variable": "velocity"
    },
    "final_equation": null,
    "done": false
  },
  {
    "step_id": 21,
    "step_type": "action",
    "reasoning": "Change initial position and time to observe the effect on position.",
    "parsed_action": {
      "action_type": "increase",
      "variable": "initial_position"
    },
    "final_equation": null,
    "done": false
  },
  {
    "step_id": 22,
    "step_type": "action",
    "reasoning": "Observe the effect of changing time on position with initial position and velocity constant.",
    "parsed_action": {
      "action_type": "increase time",
      "variable": "time"
    },
    "final_equation": null,
    "done": false
  },
  {
    "step_id": 23,
    "step_type": "action",
    "reasoning": "Observe the effect of changing time on position with initial position constant and velocity constant.",
    "parsed_action": {
      "action_type": "increase time",
      "variable": "time"
    },
    "final_equation": null,
    "done": false
  },
  {
    "step_id": 24,
    "step_type": "action",
    "reasoning": "Observe the effect of changing time on position with initial position and velocity constant.",
    "parsed_action": {
      "action_type": "increase time",
      "variable": "time"
    },
    "final_equation": null,
    "done": false
  },
  {
    "step_id": 25,
    "step_type": "action",
    "reasoning": "Change initial position and time to observe the effect on position.",
    "parsed_action": {
      "action_type": "decrease time",
      "variable": "time"
    },
    "final_equation": null,
    "done": false
  },
  {
    "step_id": 26,
    "step_type": "action",
    "reasoning": "Observe the effect of changing time on position with initial position constant and velocity constant.",
    "parsed_action": {
      "action_type": "increase time",
      "variable": "time"
    },
    "final_equation": null,
    "done": false
  },
  {
    "step_id": 27,
    "step_type": "action",
    "reasoning": "Increase time to observe the effect of velocity on position",
    "parsed_action": {
      "action_type": "increase",
      "variable": "time"
    },
    "final_equation": null,
    "done": false
  },
  {
    "step_id": 28,
    "step_type": "action",
    "reasoning": "Observe the effect of changing time on position with initial position and velocity constant.",
    "parsed_action": {
      "action_type": "increase time",
      "variable": "time"
    },
    "final_equation": null,
    "done": false
  },
  {
    "step_id": 29,
    "step_type": "action",
    "reasoning": "Observe the effect of changing velocity on position with time constant and initial position constant.",
    "parsed_action": {
      "action_type": "increase velocity",
      "variable": "velocity"
    },
    "final_equation": null,
    "done": false
  },
  {
    "step_id": 30,
    "step_type": "action",
    "reasoning": "Observe the effect of changing time on position with initial position and velocity constant.",
    "parsed_action": {
      "action_type": "increase time",
      "variable": "time"
    },
    "final_equation": null,
    "done": false
  },
  {
    "step_id": 31,
    "step_type": "action",
    "reasoning": "Observe the effect of changing time on position with initial position and velocity constant.",
    "parsed_action": {
      "action_type": "increase time",
      "variable": "time"
    },
    "final_equation": null,
    "done": false
  },
  {
    "step_id": 32,
    "step_type": "action",
    "reasoning": "Observe the effect of changing time on position with initial position and velocity constant.",
    "parsed_action": {
      "action_type": "increase time",
      "variable": "time"
    },
    "final_equation": null,
    "done": false
  },
  {
    "step_id": 33,
    "step_type": "action",
    "reasoning": "Observe the effect of changing time on position with initial position and velocity constant.",
    "parsed_action": {
      "action_type": "increase time",
      "variable": "time"
    },
    "final_equation": null,
    "done": false
  },
  {
    "step_id": 34,
    "step_type": "action",
    "reasoning": "Observe the effect of changing time on position with initial position and velocity constant.",
    "parsed_action": {
      "action_type": "increase time",
      "variable": "time"
    },
    "final_equation": null,
    "done": false
  },
  {
    "step_id": 35,
    "step_type": "action",
    "reasoning": "Observe the effect of changing time on position with initial position constant and velocity constant.",
    "parsed_action": {
      "action_type": "increase time",
      "variable": "time"
    },
    "final_equation": null,
    "done": false
  },
  {
    "step_id": 36,
    "step_type": "action",
    "reasoning": "Observe the effect of changing time on position with initial position and velocity constant.",
    "parsed_action": {
      "action_type": "increase time",
      "variable": "time"
    },
    "final_equation": null,
    "done": false
  },
  {
    "step_id": 37,
    "step_type": "action",
    "reasoning": "Observe the effect of changing time on position with initial position and velocity constant.",
    "parsed_action": {
      "action_type": "increase time",
      "variable": "time"
    },
    "final_equation": null,
    "done": false
  },
  {
    "step_id": 38,
    "step_type": "action",
    "reasoning": "Observe the effect of changing velocity on position with time constant and initial position constant.",
    "parsed_action": {
      "action_type": "increase",
      "variable": "velocity"
    },
    "final_equation": null,
    "done": false
  },
  {
    "step_id": 39,
    "step_type": "action",
    "reasoning": "Observe the effect of changing time on position with initial position and velocity constant.",
    "parsed_action": {
      "action_type": "increase time",
      "variable": "time"
    },
    "final_equation": null,
    "done": false
  },
  {
    "step_id": 40,
    "step_type": "action",
    "reasoning": "The position is increasing over time, and the rate of change is constant, so it's likely a linear equation. The initial position and velocity seem to be contributing to the position, so I'll try to isolate the effect of each.",
    "parsed_action": {
      "action_type": "decrease velocity",
      "variable": "velocity"
    },
    "final_equation": null,
    "done": false
  },
  {
    "step_id": 41,
    "step_type": "action",
    "reasoning": "Observe the effect of changing time on position with initial position constant and velocity constant.",
    "parsed_action": {
      "action_type": "increase time",
      "variable": "time"
    },
    "final_equation": null,
    "done": false
  },
  {
    "step_id": 42,
    "step_type": "action",
    "reasoning": "The position is increasing over time, and the rate of change is constant, so it's likely a linear equation. The initial position and velocity seem to be contributing to the position, so I'll try to isolate the effect of each.",
    "parsed_action": {
      "action_type": "decrease velocity",
      "variable": "velocity"
    },
    "final_equation": null,
    "done": false
  },
  {
    "step_id": 43,
    "step_type": "action",
    "reasoning": "The position is increasing over time, and the rate of change is constant, so it's likely a linear equation. The initial position and velocity seem to be contributing to the position, so I'll try to isolate the effect of each.",
    "parsed_action": {
      "action_type": "decrease time",
      "variable": "time"
    },
    "final_equation": null,
    "done": false
  },
  {
    "step_id": 44,
    "step_type": "action",
    "reasoning": "Observe the effect of changing time on position with initial position and velocity constant.",
    "parsed_action": {
      "action_type": "increase time",
      "variable": "time"
    },
    "final_equation": null,
    "done": false
  },
  {
    "step_id": 45,
    "step_type": "action",
    "reasoning": "The position is increasing over time, and the rate of change is constant, so it's likely a linear equation. The initial position and velocity seem to be contributing to the position, so I'll try to isolate the effect of each.",
    "parsed_action": {
      "action_type": "decrease time",
      "variable": "time"
    },
    "final_equation": null,
    "done": false
  },
  {
    "step_id": 46,
    "step_type": "action",
    "reasoning": "Position is increasing over time, and the rate of change is constant, so it's likely a linear equation.",
    "parsed_action": {
      "action_type": "increase",
      "variable": "velocity"
    },
    "final_equation": null,
    "done": false
  },
  {
    "step_id": 47,
    "step_type": "action",
    "reasoning": "Position is increasing over time, and the rate of change is constant, so it's likely a linear equation. Initial position and velocity seem to be contributing to the position.",
    "parsed_action": {
      "action_type": "decrease velocity",
      "variable": "velocity"
    },
    "final_equation": null,
    "done": false
  },
  {
    "step_id": 48,
    "step_type": "action",
    "reasoning": "Position is increasing over time, and the rate of change is constant, so it's likely a linear equation. Initial position and velocity seem to be contributing to the position.",
    "parsed_action": {
      "action_type": "decrease velocity",
      "variable": "velocity"
    },
    "final_equation": null,
    "done": false
  },
  {
    "step_id": 49,
    "step_type": "action",
    "reasoning": "Observe the effect of changing time on position with initial position constant and velocity constant.",
    "parsed_action": {
      "action_type": "increase time",
      "variable": "time"
    },
    "final_equation": null,
    "done": false
  },
  {
    "step_id": 50,
    "step_type": "finish",
    "reasoning": "Position is increasing over time, and the rate of change is constant, so it's likely a linear equation. Initial position and velocity seem to be contributing to the position.",
    "parsed_action": null,
    "final_equation": "position = initial_position + velocity * time",
    "done": true
  }
]