[
  {
    "step_id": 0,
    "step_type": "action",
    "reasoning": "Given the current state, Y2 seems to have a relationship with B and C but not A, as Y1 is only related to A. Let's adjust B to see if it affects Y2.",
    "parsed_action": {
      "action_type": "increase",
      "variable": "B"
    },
    "final_equation": null,
    "done": false
  },
  {
    "step_id": 1,
    "step_type": "action",
    "reasoning": "Given the observation, increasing B does not seem to affect Y2. Let's try increasing C to see if it has any influence.",
    "parsed_action": {
      "action_type": "increase",
      "variable": "C"
    },
    "final_equation": null,
    "done": false
  },
  {
    "step_id": 2,
    "step_type": "action",
    "reasoning": "Increasing C significantly affected Y2, but we don't have enough information to determine the relationship between them. Let's try decreasing C to see if it follows a linear or exponential pattern.",
    "parsed_action": {
      "action_type": "decrease",
      "variable": "C"
    },
    "final_equation": null,
    "done": false
  },
  {
    "step_id": 3,
    "step_type": "action",
    "reasoning": "Y2 seems to be linearly related to C, as increasing and decreasing C results in proportional changes in Y2. Let's verify this by increasing C again.",
    "parsed_action": {
      "action_type": "increase",
      "variable": "C"
    },
    "final_equation": null,
    "done": false
  },
  {
    "step_id": 4,
    "step_type": "action",
    "reasoning": "Y2 appears to be linearly related to C. Let's further verify this by observing Y2 when C is increased beyond its current value.",
    "parsed_action": {
      "action_type": "increase",
      "variable": "C"
    },
    "final_equation": null,
    "done": false
  },
  {
    "step_id": 5,
    "step_type": "action",
    "reasoning": "Y2 appears to be linearly related to C, and increasing C further confirms this relationship. However, to ensure the linearity, let's check if decreasing C results in proportional changes in Y2.",
    "parsed_action": {
      "action_type": "decrease",
      "variable": "C"
    },
    "final_equation": null,
    "done": false
  },
  {
    "step_id": 6,
    "step_type": "action",
    "reasoning": "Y2 appears to be linearly related to C. Let's confirm the linear relationship by observing Y2 when C is increased and decreased further.",
    "parsed_action": {
      "action_type": "increase",
      "variable": "C"
    },
    "final_equation": null,
    "done": false
  },
  {
    "step_id": 7,
    "step_type": "action",
    "reasoning": "Y2 appears to be linearly related to C, and the linear relationship seems consistent. To confirm the equation, let's adjust C slightly and observe the change in Y2.",
    "parsed_action": {
      "action_type": "increase",
      "variable": "C"
    },
    "final_equation": null,
    "done": false
  },
  {
    "step_id": 8,
    "step_type": "action",
    "reasoning": "The linear relationship between Y2 and C is confirmed by the observations. Let's further verify the slope and intercept of the line.",
    "parsed_action": {
      "action_type": "increase",
      "variable": "B"
    },
    "final_equation": null,
    "done": false
  },
  {
    "step_id": 9,
    "step_type": "action",
    "reasoning": "The linear relationship between Y2 and C is confirmed by the observations. Let's further verify the slope and intercept of the line.",
    "parsed_action": {
      "action_type": "decrease",
      "variable": "C"
    },
    "final_equation": null,
    "done": false
  }
]