{"_type": "table", "column_types": {"params": {"type_map": {"discovery_efficiency": {"params": {"allowed_types": [{"wb_type": "none"}, {"wb_type": "number"}]}, "wb_type": "union"}, "equation_correct": {"params": {"allowed_types": [{"wb_type": "boolean"}, {"wb_type": "none"}]}, "wb_type": "union"}, "error_message": {"params": {"allowed_types": [{"wb_type": "none"}, {"wb_type": "string"}]}, "wb_type": "union"}, "final_equation": {"params": {"allowed_types": [{"wb_type": "none"}, {"wb_type": "string"}]}, "wb_type": "union"}, "finish_called": {"params": {"allowed_types": [{"wb_type": "boolean"}, {"wb_type": "none"}]}, "wb_type": "union"}, "redundancy_penalty": {"params": {"allowed_types": [{"wb_type": "none"}, {"wb_type": "number"}]}, "wb_type": "union"}, "run_id": {"params": {"allowed_types": [{"wb_type": "none"}, {"wb_type": "number"}]}, "wb_type": "union"}, "state_coverage_ratio": {"params": {"allowed_types": [{"wb_type": "none"}, {"wb_type": "number"}]}, "wb_type": "union"}, "steps_to_success": {"params": {"allowed_types": [{"wb_type": "none"}, {"wb_type": "number"}]}, "wb_type": "union"}, "success": {"params": {"allowed_types": [{"wb_type": "boolean"}, {"wb_type": "none"}]}, "wb_type": "union"}, "termination_reason": {"params": {"allowed_types": [{"wb_type": "none"}, {"wb_type": "string"}]}, "wb_type": "union"}, "total_steps": {"params": {"allowed_types": [{"wb_type": "none"}, {"wb_type": "number"}]}, "wb_type": "union"}, "variable_isolation_score": {"params": {"allowed_types": [{"wb_type": "none"}, {"wb_type": "number"}]}, "wb_type": "union"}}}, "wb_type": "typedDict"}, "columns": ["run_id", "success", "equation_correct", "finish_called", "termination_reason", "total_steps", "steps_to_success", "final_equation", "state_coverage_ratio", "redundancy_penalty", "variable_isolation_score", "discovery_efficiency", "error_message"], "data": [[0, false, false, false, "parse_error", 8, null, null, 0.75, 0.375, 0.0, 0.0, "model output is not valid JSON: {\n  \"reasoning\": \"I have observed that when A=0, B=0, C=2, Y=0. When A increased to 10 with C=3, Y became 10. This suggests Y depends on A and C. Let's test if Y = A + C - 3. If A=10, C=3, then 10+3-3=10, which matches. Now I need to verify the coefficient of B. I will set A=0, C=2 (baseline) and increase B to see if Y changes linearly with B. If Y = A + C - 3 + B, then increasing B should increase Y. Wait, previous step 2 showed B=5, C=2, A=0 -> Y=10. If Y = A + 2B + C - 3? Let's re-evaluate. Step 2: A=0, B=5, C=2 -> Y=10. If Y = 2B + C - 3? 2*5 + 2 - 3 = 8 != 10. Maybe Y = 2B + A? 2*5 + 0 = 10. Yes. Step 6: A=10, B=0, C=3 -> Y=10. If Y = 2B + A, then 0 + 10 = 10. Yes. Step 5: A=0, B=0, C=2 -> Y=0. If Y = 2B + A, then 0 + 0 = 0. Yes. Step 4: A=0, B=0, C=3 -> Y=0. If Y = 2B + A, then 0 + 0 = 0. Yes. It seems Y = A + 2*B. C does not affect Y. Let's confirm by changing B again with A=0, C=2. I will increase B to 10 and check Y. If Y = 2B, then Y should be 20.\"\n  \"step_type\": \"action\",\n  \"action\": {\n    \"action_type\": \"increase\",\n    \"variable\": \"B\"\n  },\n  \"final_equation\": null\n}"], [1, true, true, true, "finish_success", 3, 3, "Y = A + B * C", 0.6667, 0.0, 0.0, 0.333333, null], [2, false, false, false, "parse_error", 2, null, null, 1.0, 0.0, 0.0, 0.0, "model output is not valid JSON: {\n  \"reasoning\": \"In Step 1, I increased C from 2.0 to 3.0 while keeping A=0.0 and B=10.0 constant. The observation shows Y changed from 20.0 to 30.0. This contradicts the hypothesis Y = 2*B (which would keep Y constant at 20) and suggests Y depends on C as well. Let's re-evaluate the relationship. At Step 0: A=0, B=5, C=2, Y=10. At Step 1: A=0, B=10, C=2, Y=20. At Step 2: A=0, B=10, C=3, Y=30. Looking at the data: When B=10, C=2, Y=20. When B=10, C=3, Y=30. The difference in C is 1, and the difference in Y is 10. This implies Y = 10*C + constant. If Y = 10*C, then for C=2, Y=20 (matches). For C=3, Y=30 (matches). Now let's check the role of B. In Step 0, B=5, C=2, Y=10. If Y = 10*C, then Y should be 20, but it is 10. So B must contribute. Let's look at the total: 10 = 10*2 + (-10)? No. Maybe Y = 10*B? If B=5, Y=50 (no). Maybe Y = 10*(B+C)? 10*(5+2)=70 (no). Let's try Y = 10*B + 10*C? 10*5 + 10*2 = 70 (no). Let's re-examine the differences. Step 0 to Step 1: B increased by 5, Y increased by 10. Ratio B->Y is 2. Step 1 to Step 2: C increased by 1, Y increased by 10. Ratio C->Y is 10. So Y = 2*B + 10*C. Let's verify with Step 0: 2*5 + 10*2 = 10 + 20 = 30. But Y was 10. This doesn't fit. Wait, maybe my initial hypothesis was wrong. Let's look at the values again. Step 0: A=0, B=5, C=2, Y=10. Step 1: A=0, B=10, C=2, Y=20. Step 2: A=0, B=10, C=3, Y=30. Is it possible Y = 10*C? Step 0: 10*2=20 != 10. Step 1: 10*2=20 == 20. Step 2: 10*3=30 == 30. So Y=10*C works for Steps 1 and 2, but not Step 0. Is there a dependency on B? Maybe Y = 10*C + k*B? For Step 0: 10*2 + k*5 = 10 => 20 + 5k = 10 => 5k = -10 => k = -2. Let's test Y = 10*C - 2*B. Step 0: 10*2 - 2*5 = 20 - 10 = 10 (Matches). Step 1: 10*2 - 2*10 = 20 - 20 = 0 (Does not match Y=20). Step 2: 10*3 - 2*10 = 30 - 20 = 10 (Does not match Y=30). This hypothesis fails. Let's try Y = 10*B? Step 0: 10*5=50 (no). Y = 2*B? Step 0: 2*5=10 (matches). Step 1: 2*10=20 (matches). Step 2: 2*10=20 (does not match Y=30). So Y depends on C. Let's try Y = 10*C. Step 0: 20 (no). Step 1: 20 (yes). Step 2: 30 (yes). Why did Step 0 fail? Maybe A is involved? Step"], [3, false, false, false, "parse_error", 4, null, null, 1.0, 0.0, 0.0, 0.0, "model output is not valid JSON: {\n  \"reasoning\": \"In Step 3, I decreased C from 2.0 to 1.0 while keeping A=0.0 and B=10.0 constant. The result was Y changing from 20.0 to 10.0. Previously, with A=0, B=10, C=2, Y was 20. With A=0, B=10, C=1, Y is 10. The change in C (-1) caused a change in Y (-10). This suggests a linear relationship between C and Y with a coefficient of -10 (since -1 * -10 = 10? No, delta C = -1, delta Y = -10, so slope is 10). Let's re-evaluate: C went 2->1 (delta -1), Y went 20->10 (delta -10). Slope dY/dC = 10. So term is 10*C. Let's check previous points: 1. A=0, B=10, C=2 -> Y=20. If Y = A + 2*B + 10*C, then 0 + 20 + 20 = 40. Incorrect. 2. A=0, B=5, C=2 -> Y=10. If Y = A + 2*B + 10*C, then 0 + 10 + 20 = 30. Incorrect. Let's reconsider the data points: (A=0, B=10, C=2, Y=20), (A=0, B=5, C=2, Y=10), (A=0, B=10, C=1, Y=10). From (0,5,2)->10 and (0,10,2)->20, doubling B doubles Y (slope 2 for B). From (0,10,2)->20 and (0,10,1)->10, halving C halves Y (slope 10 for C? No, 2->1 is half, 20->10 is half. So Y is proportional to C with factor 10? 10*2=20, 10*1=10. Yes). So Y = 2*B + 10*C? Let's check A. In Step 1, A went 0->10, B=5, C=2, Y went 10->20. Delta A=10, Delta Y=10. Slope 1 for A. So Y = A + 2*B + 10*C? Check (0,5,2): 0 + 10 + 20 = 30 != 10. Something is wrong. Let's re-read Step 1. Step 0: A=0, B=10, C=2, Y=20. Step 1: increase A to 10. State before: A=0, B=5, C=2, Y=10. Wait, the history says 'state before' in Step 1 is A=0, B=5, C=2, Y=10. But the initial observation says A=0, B=10, C=2, Y=20. There is a discrepancy in the provided history text vs the initial observation. Let's look at the history provided in the prompt carefully. 'Step 0: ... state before: {'A': 0.0, 'B': 5.0, 'C': 2.0, 'Y': 10.0} state after: {'A': 10.0, 'B': 5.0, 'C': 2.0, 'Y': 20.0}'. This implies the starting state for Step 0 was A=0, B=5, C=2, Y=10. But the 'Current observation' at the very top says A=0, B=10, C=1, Y=10. And 'Current state' says A=0, B=10, C=1, Y=10. The history seems to describe a different starting point or I am misinterpreting the 'state before' in the history log. Let's trust the 'Current observation' at the end of the prompt: A=0, B=10, C=1, Y=10. And the history steps. Step 3 ended with A=0, B=10, C=1, Y=10. This matches the current observation. So the current state is consistent with Step"], [4, false, false, true, "finish_wrong", 8, null, "Y = A + 2*B", 0.75, 0.25, 0.0, 0.0, null], [5, false, false, true, "finish_wrong", 4, null, "Y = A + 2*B + 10*C - 20", 0.75, 0.0, 0.0, 0.0, null], [6, false, false, true, "finish_wrong", 3, null, "Y = A + B + C + 3", 0.6667, 0.0, 0.0, 0.0, null], [7, false, false, false, "parse_error", 4, null, null, 1.0, 0.25, 0.0, 0.0, "model output is not valid JSON: {\n  \"reasoning\": \"I have collected sufficient data points to determine the equation. From Step 0 and 1, I established Y = 2*B when A=0. From Step 2, I found that when B and C were constant, increasing A by 10 increased Y by 10, implying a coefficient of 1 for A (Y = A + ...). From Step 3, I observed that when A=10, B=15, C increased from 2 to 3, Y increased from 40 to 55 (a change of 15). The change in B was 0, the change in A was 0. The change in Y (15) equals the change in C (1) multiplied by 15? No, wait. Let's re-evaluate Step 3. Previous state (Step 2): A=10, B=15, C=2, Y=30? No, Step 2 result was Y=40? Let's re-read the history carefully.\\n\\nRe-evaluating History:\\nStep 0 Start: A=0, B=5, C=2, Y=10. (Hypothesis Y=2B holds: 2*5=10).\\nStep 0 Action: Increase B. Result: A=0, B=10, C=2, Y=20. (2*10=20). Confirms Y=2B.\\nStep 1 Action: Increase B. Result: A=0, B=15, C=2, Y=30. (2*15=30). Confirms Y=2B.\\nStep 2 Action: Increase A. Result: A=10, B=15, C=2, Y=40. (Previous Y=30). Change in A=10, Change in Y=10. Ratio A:Y = 1:1. So Y includes +1*A. Current Y = A + 2B = 10 + 30 = 40. Matches.\\nStep 3 Action: Increase C. Result: A=10, B=15, C=3, Y=55. (Previous Y=40). Change in C=1, Change in Y=15. Wait. Change in Y is 55-40=15. Change in C is 1. This implies coefficient for C is 15? Or did I misread the previous Y?\\n\\nLet's re-read Step 2 result: {'A': 10.0, 'B': 15.0, 'C': 2.0, 'Y': 40.0}. Correct.\\nStep 3 result: {'A': 10.0, 'B': 15.0, 'C': 3.0, 'Y': 55.0}. Correct.\\nDelta C = +1. Delta Y = +15. So coefficient for C is 15? That seems odd given A and B coefficients are 1 and 2. Let's check the current observation provided in the prompt: A=10, B=15, C=3, Y=55. This matches the Step 3 result.\\n\\nLet's re-calculate potential equation: Y = A + 2B + 15C? 10 + 30 + 45 = 85 != 55. No.\\nMaybe Y = A + 2B + C? 10 + 30 + 3 = 43 != 55. No.\\nMaybe Y = A + 2B + 10C? 10 + 30 + 30 = 70. No.\\nMaybe Y = A + 2B + 5C? 10 + 30 + 15 = 55. YES. Coefficient for C is 5.\\n\\nLet's verify with Step 0: A=0, B=5, C=2. Y = 0 + 2*5 + 5*2 = 10 + 10 = 20. But observed Y was 10. Contradiction.\\n\\nLet's re-read the history very carefully. Maybe I misinterpreted the variable names or values.\\nStep 0 Start: A=0, B=5, C=2, Y=10.\\nStep 0 Action: Increase B. Result: A=0, B=10, C=2, Y=20.\\nStep 1 Action: Increase B. Result: A=0, B=15, C=2, Y"], [8, false, false, false, "parse_error", 3, null, null, 1.0, 0.0, 0.0, 0.0, "model output is not valid JSON: {\n  \"reasoning\": \"I have observed the following data points: 1) A=0, B=5, C=2 -> Y=10; 2) A=10, B=5, C=2 -> Y=20; 3) A=10, B=10, C=2 -> Y=30; 4) A=10, B=10, C=1 -> Y=20. Let's test the hypothesis Y = A + B + C. Point 1: 0+5+2=7 (observed 10, mismatch). Point 2: 10+5+2=17 (observed 20, mismatch). Point 3: 10+10+2=22 (observed 30, mismatch). Point 4: 10+10+1=21 (observed 20, mismatch). The simple sum doesn't work. Let's look at differences. From step 0 to 1: A increased by 10, Y increased by 10. From step 1 to 2: B increased by 5, Y increased by 10. From step 2 to 3: C decreased by 1, Y decreased by 10. This suggests A contributes 1 per unit, B contributes 2 per unit, and C contributes -10 per unit? Let's re-evaluate. If Y = A + 2B - 10C. Step 0: 0 + 2(5) - 10(2) = 10 - 20 = -10 (mismatch with 10). Maybe the coefficients are different. Let's try Y = A + 2B + C? Step 0: 0+10+2=12 (close to 10). Step 2: 10+20+2=32 (close to 30). Step 3: 10+20+1=31 (close to 20). Not quite. Let's look at the changes again. Delta A=10 -> Delta Y=10. Delta B=5 -> Delta Y=10. Delta C=-1 -> Delta Y=-10. So dY/dA = 1, dY/dB = 2, dY/dC = -10. Equation form: Y = A + 2B - 10C + k. Using Step 0: 10 = 0 + 10 - 20 + k => 10 = -10 + k => k=20. Let's test Y = A + 2B - 10C + 20. Step 0: 0 + 10 - 20 + 20 = 10. Correct. Step 1: 10 + 10 - 20 + 20 = 20. Correct. Step 2: 10 + 20 - 20 + 20 = 30. Correct. Step 3: 10 + 20 - 10 + 20 = 40 (Wait, step 3 observation was Y=20). My calculation for step 3: A=10, B=10, C=1. 10 + 2(10) - 10(1) + 20 = 10 + 20 - 10 + 20 = 40. But observed Y is 20. So the formula is wrong. Let's re-examine the data. Step 0: A=0, B=5, C=2, Y=10. Step 1: A=10, B=5, C=2, Y=20. Change A+10 -> Y+10. Step 2: A=10, B=10, C=2, Y=30. Change B+5 -> Y+10. Step 3: A=10, B=10, C=1, Y=20. Change C-1 -> Y-10. So dY/dA = 1, dY/dB = 2, dY/dC = -10. Wait, step 3: C went from 2 to 1 (delta -1), Y went from 30 to 20 (delta -10). So dY/dC = 10. Ah, -1 * 10 = -10. So dY/dC = 10. Let's re-calculate. dY/dA = 1. d"], [9, false, false, true, "finish_wrong", 4, null, "Y = A + 2*B + 10*C - 20", 0.75, 0.0, 0.0, 0.0, null], [10, false, false, false, "parse_error", 2, null, null, 1.0, 0.0, 0.0, 0.0, "model output is not valid JSON: {\n  \"reasoning\": \"Based on the history, Step 0 showed Y=10 when B=5 (A=0, C=2), suggesting Y=2B. Step 1 increased B to 10, and Y became 20, confirming Y=2B. Step 2 increased C to 3 while keeping B=10 and A=0, and Y became 30. If the relationship were Y=2B, Y should remain 20. Since Y increased to 30, C must also contribute. The change in C was +1.0, and the change in Y was +10.0. This suggests a coefficient of 10 for C (10 * 1 = 10). Testing the hypothesis Y = 2*B + 10*C: With A=0, B=10, C=3, Y = 2*10 + 10*3 = 20 + 30 = 50. But the observed Y is 30. Let's re-evaluate. Maybe the coefficient for C is different or A is involved. Let's look at the ratio again. In Step 1, B went 5->10 (+5), Y went 10->20 (+10). Ratio Y/B = 2. In Step 2, C went 2->3 (+1), Y went 20->30 (+10). Ratio Y/C change = 10. If Y = m*A + n*B + p*C. From Step 0->1: 0*A + 5*B + 2*C -> 10 + 10 = 20. So 5n = 10 => n=2. From Step 1->2: 0*A + 10*B + 1*C -> 20 + 10 = 30. So 1*p = 10 => p=10. So Y = 2B + 10C? Let's check Step 0: 2*5 + 10*2 = 10 + 20 = 30. But observed Y was 10. Contradiction. My previous assumption that A=0, B=5, C=2 yielded Y=10 was correct in the history text, but my calculation 2*5 + 10*2 = 30 contradicts Y=10. Wait, the history says Step 0: A=0, B=5, C=2, Y=10. Step 1: A=0, B=10, C=2, Y=20. Step 2: A=0, B=10, C=3, Y=30. Let's re-calculate the differences. Step 0 to 1: Delta B = +5, Delta Y = +10. So n = 10/5 = 2. Step 1 to 2: Delta C = +1, Delta Y = +10. So p = 10/1 = 10. So Y = 2B + 10C? Check Step 0: 2*5 + 10*2 = 30 != 10. Something is wrong. Is it possible the equation is Y = 2B + 10*(C-2)? No, that's arbitrary. Let's look at the numbers again. 10, 20, 30. B is 5, 10, 10. C is 2, 2, 3. A is 0, 0, 0. When B=5, Y=10. When B=10, Y=20. When B=10, C=3, Y=30. It seems Y depends on B and C. Maybe Y = 2*B + 10*(C-2)? If C=2, term is 0, Y=2*5=10. If C=3, term is 10, Y=2*10+10=30. This fits! But usually equations are simpler like Y = m*A + n*B + k*C. Let's try Y = 2*B + 10*C - 20? Check: 2*5 + 10*2 - 20 = 10+20-20=10. 2*10 + 10*2 - 20 = 20+20-20=20. 2*10 + 10*3 - 20 = 20+30-20=30. This works. Is there"], [11, false, false, true, "finish_wrong", 4, null, "Y = A + 2*B", 0.75, 0.0, 0.0, 0.0, null], [12, false, false, false, "parse_error", 3, null, null, 1.0, 0.0, 0.0, 0.0, "model output is not valid JSON: {\n  \"reasoning\": \"Based on Step 0, when A increases by 10 (0->10) while B=5, C=2, Y increases by 10 (10->20). This implies a coefficient of 1 for A. Based on Step 1, when B increases by 5 (5->10) while A=10, C=2, Y increases by 10 (20->30). This implies a coefficient of 2 for B (since 5*2=10). Based on Step 2, when C decreases by 1 (2->1) while A=10, B=10, Y decreases by 10 (30->20). This implies a coefficient of 10 for C (since 1*10=10). Let's verify the proposed equation Y = A + 2*B + 10*C. Using initial values A=10, B=10, C=1: Y = 10 + 2*10 + 10*1 = 10 + 20 + 10 = 40. But the current Y is 20.0. My previous deduction about C might be wrong or the base equation is different. Let's re-evaluate. Step 2: A=10, B=10, C=2 -> Y=30. C=1 -> Y=20. Change in C is -1, Change in Y is -10. So coeff of C is 10. Equation candidate: Y = A + 2B + 10C? Check Step 0: A=0, B=5, C=2 -> Y=0 + 10 + 20 = 30. But observed Y=10. So the coefficients are not constant or the form is different. Let's look at the deltas again. Step 0: dA=10, dB=0, dC=0, dY=10. Slope A = 1. Step 1: dA=0, dB=5, dC=0, dY=10. Slope B = 2. Step 2: dA=0, dB=0, dC=-1, dY=-10. Slope C = 10. Sum of slopes * vars? 1*A + 2*B + 10*C. At Step 2 state (A=10, B=10, C=1): 10 + 20 + 10 = 40. Observed Y=20. This doesn't match. Maybe the equation is Y = A + B + C + constant? Step 0: 0+5+2+k = 10 => k=3. Check Step 1: 10+10+2+3 = 25. Observed 30. No. Maybe Y = A + B + C + A*B? Step 0: 0+5+2+0 = 7 != 10. Maybe Y = A + B + C + A? Step 0: 0+5+2+0 = 7. Maybe Y = A + B + C + B? Step 0: 0+5+2+5 = 12. No. Let's re-read the observations carefully. Step 0: A=0, B=5, C=2, Y=10. Step 1: A=10, B=5, C=2, Y=20. (Delta A=10, Delta Y=10). Step 2: A=10, B=10, C=2, Y=30. (Delta B=5, Delta Y=10). Step 3: A=10, B=10, C=1, Y=20. (Delta C=-1, Delta Y=-10). Let's try Y = A + 2*B + 10*C again. Step 0: 0 + 10 + 20 = 30 != 10. Is it possible the variables are multiplied differently? Or maybe Y = A + B + C + something else. Let's look at Y - (A+B+C). Step 0: 10 - 7 = 3. Step 1: 30 - 25 = 5. Step 2: 20 - 21 = -1. No pattern. Let's try Y = A + B + C + A*B? Step 0: 7 + 0 = 7. Step 1: 25 + 100 = 1"], [13, false, false, false, "parse_error", 4, null, null, 1.0, 0.0, 0.0, 0.0, "model output is not valid JSON: {\n  \"reasoning\": \"In Step 3, I decreased B from 10 to 5 while keeping A=10 and C=1 constant. Y changed from 20 to 15. This confirms Y depends on B. With A=10, C=1, B=10 -> Y=20; B=5 -> Y=15. The change in B is -5, change in Y is -5, suggesting Y = B. Combining previous findings: when B=10, C=1, A=0 -> Y=10. If Y = A + 10*C + B, then 0 + 10*1 + 10 = 20 (matches Step 2). If B=5, A=10, C=1, then 10 + 10*1 + 5 = 25, but observed Y is 15. So the coefficient of B is not 1. Let's re-evaluate. Step 0: A=0, B=5, C=2, Y=10. Step 1: A=0, B=10, C=2, Y=20. Step 2: A=0, B=10, C=1, Y=10. Step 3: A=10, B=10, C=1, Y=20. Step 4: A=10, B=5, C=1, Y=15. Let's test Y = A + 10*C + 0*B? No, Step 4 gives 10+10=20 != 15. Test Y = A + 5*C + 0*B? Step 2: 0+5*1=5 != 10. Test Y = A + 10*C + k*B. Step 2: 0 + 10 + 10k = 20 => 10k=10 => k=1. Step 4: 10 + 10 + 5 = 25 != 15. Contradiction. Maybe Y = A + 10*C - k*B? Step 2: 0 + 10 - 10k = 20 => -10k=10 => k=-1. Step 4: 10 + 10 - (-1)*5 = 25 != 15. Maybe Y = A + 5*C + 5*B? Step 2: 0 + 5 + 50 = 55 != 20. Let's re-examine Step 0 to Step 1. A=0, B=5, C=2, Y=10. A=0, B=10, C=2, Y=20. Delta B=5, Delta Y=10. Slope B=2. Step 1 to Step 2. B=10, C=2->1, Y=20->10. Delta C=-1, Delta Y=-10. Slope C=10. Step 2 to Step 3. A=0->10, Y=10->20. Delta A=10, Delta Y=10. Slope A=1. Step 3 to Step 4. B=10->5, Y=20->15. Delta B=-5, Delta Y=-5. Slope B=1. Wait, Step 0->1 gave slope 2. Step 3->4 gave slope 1. This implies the relationship is not linear or I misread the data. Let's re-read Step 0 state after: {'A': 0.0, 'B': 10.0, 'C': 2.0, 'Y': 20.0}. Yes. Step 3 state after: {'A': 10.0, 'B': 5.0, 'C': 1.0, 'Y': 15.0}. Yes. Let's try Y = A + 10*C + B? Step 0: 0 + 20 + 5 = 25 != 10. Step 0: 0 + 10*2 + 5 = 25. No. Maybe Y = A + 5*C + 0*B? Step 2: 0 + 5 = 5 != 10. Maybe Y = A + 10*C + 0*B? Step 2: 10 != 20. Maybe Y = 2*A + 10*C? Step 3: 20 + 10 = 3"], [14, false, false, false, "parse_error", 3, null, null, 1.0, 0.0, 0.0, 0.0, "model output is not valid JSON: {\n  \"reasoning\": \"Based on the observations: Step 0 shows Y=20 when B=10 (A=0, C=2). Step 1 shows Y=30 when A=10 (B=10, C=2). Step 2 shows Y=40 when C=3 (A=10, B=10). Comparing Step 1 and Step 2: A=10, B=10, C changes from 2 to 3, but Y changes from 30 to 40. This contradicts the hypothesis that C has no effect. Let's re-evaluate. If Y = A + 2*B + C, then 10 + 20 + 3 = 33 (not 40). If Y = A + 2*B + 2*C, then 10 + 20 + 6 = 36 (not 40). Let's look at the changes again. Step 0: A=0, B=10, C=2 -> Y=20. Step 1: A=10, B=10, C=2 -> Y=30. Change in A (+10) -> Change in Y (+10). So coefficient of A is 1. Step 2: A=10, B=10, C=2 -> Y=30. Step 3 (current): A=10, B=10, C=3 -> Y=40. Change in C (+1) -> Change in Y (+10). So coefficient of C is 10. Now check B. Step 0: A=0, B=10, C=2 -> Y=20. Hypothesis: Y = A + k*B + 10*C. 20 = 0 + 10k + 20 => 10k = 0 => k=0? No, that would mean B doesn't matter. Let's re-examine Step 0. A=0, B=10, C=2, Y=20. If Y = A + 2*B + 2*C? 0 + 20 + 4 = 24 != 20. If Y = A + B + C? 0+10+2=12 != 20. Let's try Y = 2*A + 2*B + 2*C? 0+20+4=24. Let's try Y = A + 2*B + C? 0+20+2=22. Let's try Y = A + 2*B + 2*C? 24. Wait, let's look at Step 0 again. A=0, B=10, C=2, Y=20. Maybe Y = 2*B? 2*10=20. Yes. Step 1: A=10, B=10, C=2, Y=30. 2*B=20. But Y=30. So A contributes 10. Y = A + 2*B. Check: 10 + 20 = 30. Yes. Step 2: A=10, B=10, C=2, Y=30. Matches. Step 3: A=10, B=10, C=3, Y=40. If Y = A + 2*B, then 10+20=30. But Y=40. So C must contribute 10. Change in C is +1, change in Y is +10. So coefficient of C is 10. Equation: Y = A + 2*B + 10*C. Let's verify Step 0: 0 + 20 + 20 = 40. But Y=20. Contradiction. My previous deduction for Step 0 was Y=20. If Y = A + 2*B + 10*C, then 0 + 20 + 20 = 40 != 20. So C coefficient is not 10? Let's re-read the history. Step 0: A=0, B=10, C=2, Y=20. Step 1: A=10, B=10, C=2, Y=30. Step 2: A=10, B=10, C=3, Y=40. Wait, Step 2 says Y=40. If Y = A + 2*B + k*C. Step 1: 10 + 20 + 2k = 3"], [15, false, false, false, "parse_error", 3, null, null, 1.0, 0.0, 0.0, 0.0, "model output is not valid JSON: {\n  \"reasoning\": \"I have observed three data points: (A=0, B=5, C=2, Y=10), (A=10, B=5, C=2, Y=20), and (A=10, B=10, C=2, Y=30). The last step changed C from 2 to 1 while keeping A=10 and B=10, and Y dropped from 30 to 20. This change in C caused a large change in Y, suggesting C is a significant factor. Let's test the hypothesis Y = A + 2B + 3C. Step 0: 0 + 10 + 6 = 16 (Actual 10). No. Let's try Y = A + 2B + C. Step 0: 0 + 10 + 2 = 12 (Actual 10). No. Let's try Y = A + 2B + 2C. Step 0: 0 + 10 + 4 = 14 (Actual 10). No. Let's re-examine the steps. Step 0: A=0, B=5, C=2, Y=10. Step 1: A=10, B=5, C=2, Y=20. Delta A=10, Delta Y=10. Step 2: A=10, B=10, C=2, Y=30. Delta B=5, Delta Y=10. Step 3: A=10, B=10, C=1, Y=20. Delta C=-1, Delta Y=-10. So, dY/dA = 1, dY/dB = 2, dY/dC = -10. The equation should be Y = A + 2B - 10C + constant. Let's find the constant using Step 0: 10 = 0 + 2*5 - 10*2 + k => 10 = 10 - 20 + k => 10 = -10 + k => k = 20. So the hypothesis is Y = A + 2B - 10C + 20. Let's verify with all steps. Step 0: 0 + 10 - 20 + 20 = 10. Correct. Step 1: 10 + 10 - 20 + 20 = 20. Correct. Step 2: 10 + 20 - 20 + 20 = 30. Correct. Step 3: 10 + 20 - 10 + 20 = 40. Wait, Step 3 observed Y=20. My calculation gives 40. There is a discrepancy. Let's re-read Step 3 observation. State before: A=10, B=10, C=2, Y=30. State after: A=10, B=10, C=1, Y=20. Delta C = -1, Delta Y = -10. So dY/dC = 10. My previous calculation dY/dC = -10 was wrong because I subtracted the wrong way. If C decreases by 1, Y decreases by 10. So coefficient of C is +10? If Y = ... + 10C, then decreasing C by 1 decreases Y by 10. Yes. So dY/dC = 10. Let's re-evaluate. dY/dA = 1. dY/dB = 2. dY/dC = 10. Equation: Y = A + 2B + 10C + k. Step 0: 10 = 0 + 10 + 20 + k => 10 = 30 + k => k = -20. So Y = A + 2B + 10C - 20. Let's verify. Step 0: 0 + 10 + 20 - 20 = 10. Correct. Step 1: 10 + 10 + 20 - 20 = 20. Correct. Step 2: 10 + 20 + 20 - 20 = 30. Correct. Step 3: 10 + 20 + 10 - 20 = 20. Correct. The equation is Y = A + 2B + 10C - 20. I have enough evidence"], [16, false, false, false, "parse_error", 4, null, null, 1.0, 0.0, 0.0, 0.0, "model output is not valid JSON: {\n  \"reasoning\": \"I have collected four data points: (1) A=10, B=5, C=2, Y=20; (2) A=10, B=10, C=2, Y=30; (3) A=0, B=10, C=2, Y=20; (4) A=0, B=10, C=3, Y=30. Comparing points 3 and 4, when C increases from 2 to 3 (delta C = +1), Y increases from 20 to 30 (delta Y = +10). This suggests a coefficient of 10 for C. Comparing points 1 and 2, when B increases by 5, Y increases by 10, suggesting a coefficient of 2 for B. Comparing points 1 and 3, when A decreases by 10, Y decreases by 10, suggesting a coefficient of 1 for A. The proposed equation is Y = A + 2B + 10C. Let's verify with all points: 1) 10 + 2*5 + 10*2 = 10+10+20=40 != 20. My previous deduction was wrong. Let's re-examine. Point 1: A=10, B=5, C=2, Y=20. Point 2: A=10, B=10, C=2, Y=30. Delta B=5, Delta Y=10 -> coeff B = 2. Point 3: A=0, B=10, C=2, Y=20. Delta A=-10, Delta Y=-10 (from P2 to P3) -> coeff A = 1. Point 4: A=0, B=10, C=3, Y=30. Delta C=1, Delta Y=10 (from P3 to P4) -> coeff C = 10. Equation: Y = A + 2B + 10C. Check P1: 10 + 10 + 20 = 40. But Y is 20. Something is inconsistent. Let's re-read the history carefully. Step 0: A=0, B=5, C=2, Y=10. Step 1: A=10, B=5, C=2, Y=20. Step 2: A=10, B=10, C=2, Y=30. Step 3: A=0, B=10, C=2, Y=20. Step 4: A=0, B=10, C=3, Y=30. Okay, let's re-calculate coefficients based on these specific transitions. P0 (0,5,2,10) -> P1 (10,5,2,20): Delta A=10, Delta Y=10 -> coeff A = 1. P1 (10,5,2,20) -> P2 (10,10,2,30): Delta B=5, Delta Y=10 -> coeff B = 2. P2 (10,10,2,30) -> P3 (0,10,2,20): Delta A=-10, Delta Y=-10 -> coeff A = 1. P3 (0,10,2,20) -> P4 (0,10,3,30): Delta C=1, Delta Y=10 -> coeff C = 10. So Y = A + 2B + 10C. Let's check P0: 0 + 2*5 + 10*2 = 10 + 20 = 30. But Y is 10. This equation doesn't fit P0. Is there an intercept? Y = A + 2B + 10C + k. P0: 30 + k = 10 => k = -20. Let's check others. P1: 10 + 10 + 20 - 20 = 20. Correct. P2: 10 + 20 + 20 - 20 = 30. Correct. P3: 0 + 20 + 20 - 20 = 20. Correct. P4: 0 + 20 + 30 - 20 = 30. Correct. The equation is Y = A + 2B + 10C"], [17, false, false, true, "finish_wrong", 2, null, "Y = 2 * B", 0.5, 0.0, 0.0, 0.0, null], [18, false, false, true, "finish_wrong", 6, null, "Y = 2*A + 2*B + 5*C", 0.6667, 0.0, 0.0, 0.0, null], [19, false, false, false, "parse_error", 2, null, null, 1.0, 0.0, 0.0, 0.0, "model output is not valid JSON: {\n  \"reasoning\": \"The current state shows A=0.0, B=10.0, C=3.0, Y=30.0. Based on previous steps, I hypothesized Y = 2*B + 2*C. Let's verify: 2*10 + 2*3 = 20 + 6 = 26, which does not match Y=30. My previous reasoning in Step 1 was flawed because the state transition in Step 0 was inconsistent with the reported state after (B went 5->10, Y 10->20, implying Y=2B+constant, but C changed from 2 to 3 in Step 1). Let's re-evaluate. In Step 0, B=5, C=2, Y=10. In Step 1, B=10, C=2, Y=20. This implies Y = 2*B (since 2*5=10, 2*10=20). Then in Step 1, C changed to 3, and Y became 30. If Y = 2*B + 2*C, then 2*10 + 2*3 = 26 != 30. If Y = 2*B + 3*C, then 2*10 + 3*3 = 29 != 30. If Y = 2*B + 4*C, then 2*10 + 4*3 = 20 + 12 = 32 != 30. Wait, let's look at the numbers again. B=10, C=3, Y=30. Maybe Y = B + 2*C? 10 + 6 = 16. No. Maybe Y = 3*B? 30. But in Step 0, B=5, Y=10. 3*5=15 != 10. Maybe Y = 2*B + C? 20 + 3 = 23. No. Let's try Y = 2*B + 2*C again. 20+6=26. What if the relationship is Y = 2*B + 2*C + something? Or maybe Y = 3*B + C? 30+3=33. Let's try changing B to 11 to see the pattern. If Y = 2*B + 2*C, changing B by 1 should change Y by 2. If Y = 2*B + 3*C, changing B by 1 should change Y by 2. Let's test increasing B to 11. If the equation is Y = 2*B + 2*C, then Y should be 2*11 + 2*3 = 22 + 6 = 28. If the equation is Y = 2*B + 3*C, then Y = 22 + 9 = 31. If the equation is Y = 2*B + 4*C, then Y = 22 + 12 = 34. Let's try increasing B to 11.\"\n  \"step_type\": \"action\",\n  \"action\": {\n    \"action_type\": \"increase\",\n    \"variable\": \"B\"\n  },\n  \"final_equation\": null\n}"], [20, false, false, false, "parse_error", 4, null, null, 0.75, 0.0, 0.0, 0.0, "model output is not valid JSON: {\n  \"reasoning\": \"The data collected so far supports the equation Y = A + 2*B - 10*C. Step 0 confirmed slope A = 1. Step 1 confirmed slope B = 2. Step 2 showed C=2->1 caused Y=30->20 (slope -10). Step 3 confirmed C=1->2 caused Y=20->30 (slope -10). The current state is A=10, B=10, C=2, Y=30. Plugging in: 10 + 2*10 - 10*2 = 10 + 20 - 20 = 10. This does not match Y=30. Wait, let me re-evaluate the coefficients based on the steps. Step 0: A:0->10, Y:10->20. Delta A=10, Delta Y=10. Slope A = 1. Step 1: B:5->10, Y:20->30. Delta B=5, Delta Y=10. Slope B = 2. Step 2: C:2->1, Y:30->20. Delta C=-1, Delta Y=-10. Slope C = 10. Step 3: C:1->2, Y:20->30. Delta C=1, Delta Y=10. Slope C = 10. So the equation is Y = A + 2*B + 10*C. Let's check the current state: A=10, B=10, C=2. Y = 10 + 2*10 + 10*2 = 10 + 20 + 20 = 50. But the observed Y is 30. There is a contradiction in my derivation or the data. Let's re-read Step 2. State before: A=10, B=10, C=2, Y=30. Action: decrease C. State after: A=10, B=10, C=1, Y=20. Delta C = -1, Delta Y = -10. Slope C = 10. So Y = A + 2B + 10C. Check Step 0: A=0, B=5, C=2, Y=10. Formula: 0 + 10 + 20 = 30. But observed Y=10. Contradiction. Let's re-read Step 0. State before: A=0, B=5, C=2, Y=10. State after: A=10, B=5, C=2, Y=20. Delta A=10, Delta Y=10. Slope A = 1. Let's re-read Step 1. State before: A=10, B=5, C=2, Y=20. State after: A=10, B=10, C=2, Y=30. Delta B=5, Delta Y=10. Slope B = 2. Let's re-read Step 2. State before: A=10, B=10, C=2, Y=30. State after: A=10, B=10, C=1, Y=20. Delta C=-1, Delta Y=-10. Slope C = 10. Let's re-read Step 3. State before: A=10, B=10, C=1, Y=20. State after: A=10, B=10, C=2, Y=30. Delta C=1, Delta Y=10. Slope C = 10. Okay, the slopes are A=1, B=2, C=10. But the intercept calculation from Step 0 (A=0, B=5, C=2, Y=10) gives: 0 + 2*5 + 10*2 = 20. But Y=10. Difference is -10. Maybe there is a constant term? Y = A + 2B + 10C + k. 10 = 0 + 10 + 20 + k => k = -20. Let's check other points. Step 1: A=10, B=10, C=2, Y=30. Formula: 10 + 20 + 20 - 20 = 30. Matches. Step 2: A=10, B="], [21, false, false, true, "finish_wrong", 4, null, "Y = A + 2*B - 10*C", 0.75, 0.0, 0.0, 0.0, null], [22, false, false, true, "finish_wrong", 4, null, "Y = A + 2*B - 10*C", 0.75, 0.0, 0.0, 0.0, null], [23, false, false, false, "parse_error", 3, null, null, 1.0, 0.0, 0.0, 0.0, "model output is not valid JSON: {\n  \"reasoning\": \"I have gathered sufficient data to determine the equation. From Step 0, increasing A by 10 increased Y by 10 (slope 1). From Step 1, increasing B by 5 increased Y by 10 (slope 2). From Step 2, increasing C by 1 increased Y by 10 (slope 10). The current state is A=10, B=10, C=3, Y=40. Testing the hypothesis Y = A + 2*B + 10*C: 10 + 2*10 + 10*3 = 10 + 20 + 30 = 60, which does not match Y=40. Let's re-evaluate the slopes based on the actual changes observed. Step 0: Delta A = +10, Delta Y = +10. Slope A = 1. Step 1: Delta B = +5, Delta Y = +10. Slope B = 2. Step 2: Delta C = +1, Delta Y = +10. Slope C = 10. Wait, let's re-calculate the constant term. If Y = A + 2B + k*C. At A=10, B=10, C=2, Y=30. 10 + 20 + 2k = 30 => 30 + 2k = 30 => k=0. So Y = A + 2B. Let's check Step 0: A=10, B=5, Y=20. 10 + 2*5 = 20. Correct. Step 1: A=10, B=10, Y=30. 10 + 2*10 = 30. Correct. Step 2: A=10, B=10, C=3, Y=40. If Y = A + 2B, then Y should be 30. But Y is 40. This means C does affect Y. The change in Y from C=2 to C=3 was +10. So Slope C = 10. Let's re-evaluate the full equation. Y = A + 2*B + m*C. Using Step 1 data (A=10, B=10, C=2, Y=30): 10 + 20 + 2m = 30 => 30 + 2m = 30 => m=0. This contradicts Step 2 where C changes and Y changes. Is it possible the relationship is different? Let's look at the absolute values. Step 0: 10 + 2*5 = 20. Matches Y=20. Step 1: 10 + 2*10 = 30. Matches Y=30. Step 2: 10 + 2*10 = 30. But Y=40. The difference is exactly 10, which corresponds to the change in C (from 2 to 3). So the term involving C must be 10*C. Let's test Y = A + 2*B + 10*C. Step 0: 10 + 10 + 20 = 40. But Y=20. This doesn't work. Let's try Y = A + 2*B + 10*(C - base_C)? No. Let's re-read the observations carefully. Step 0: A=0, B=5, C=2, Y=10. Step 1: A=10, B=5, C=2, Y=20. Delta A=10, Delta Y=10. Slope A=1. Step 2: A=10, B=10, C=2, Y=30. Delta B=5, Delta Y=10. Slope B=2. Step 3: A=10, B=10, C=3, Y=40. Delta C=1, Delta Y=10. Slope C=10. So the equation is Y = 1*A + 2*B + 10*C + K. Let's find K using Step 0: 1*0 + 2*5 + 10*2 + K = 10 => 0 + 10 + 20 + K = 10 => 30 + K = 10 => K = -20. Let's verify with Step 1: 1*10 + 2*5 + 10"], [24, false, false, true, "finish_wrong", 4, null, "Y = A + 2*B + 10*C", 0.75, 0.0, 0.0, 0.0, null], [25, false, false, false, "parse_error", 5, null, null, 0.8, 0.2, 0.0, 0.0, "model output is not valid JSON: {\n  \"reasoning\": \"I have collected sufficient data points to determine the equation. From Step 0-1 and Step 1-2, increasing A by 10 resulted in an increase in Y by 10, indicating a coefficient of 1 for A. From Step 2-3, changing B from 0 to 5 (delta +5) resulted in Y changing from 20 to 30 (delta +10), indicating a coefficient of 2 for B. From Step 4, changing C from 2 to 3 (delta +1) resulted in no change in Y (30 to 35? Wait, let me re-read Step 4 output. State after Step 4 is A=20, B=5, C=3, Y=35. Previous state was A=20, B=5, C=2, Y=30. So delta C=1, delta Y=5. This contradicts my previous deduction that C has coefficient 0. Let me re-evaluate all points carefully.\\n\\nPoints:\\n1. A=10, B=5, C=2, Y=20\\n2. A=20, B=5, C=2, Y=30 -> Delta A=10, Delta Y=10 -> Coeff A = 1.\\n3. A=20, B=0, C=2, Y=20 -> Delta B=-5, Delta Y=-10 -> Coeff B = 2.\\n4. A=20, B=5, C=2, Y=30 -> Confirms point 2.\\n5. A=20, B=5, C=3, Y=35 -> Delta C=1, Delta Y=5 -> Coeff C = 5.\\n\\nLet's check the equation Y = A + 2*B + 5*C.\\nPoint 1: 10 + 2*5 + 5*2 = 10 + 10 + 10 = 30. But observed Y is 20. This doesn't fit.\\n\\nLet's re-examine the data. Maybe I misread the steps or the relationship is more complex.\\nLet's look at the differences again.\\nPoint 1 (Step 0): A=10, B=5, C=2, Y=20.\\nPoint 2 (Step 1): A=20, B=5, C=2, Y=30. (Delta A=10, Delta Y=10). Coeff A = 1.\\nPoint 3 (Step 2): A=20, B=0, C=2, Y=20. (Delta B=-5, Delta Y=-10). Coeff B = 2.\\nPoint 4 (Step 4): A=20, B=5, C=3, Y=35. (Delta C=1, Delta Y=5). Coeff C = 5.\\n\\nIf Coeff A=1, Coeff B=2, Coeff C=5. Constant term? Let's plug into Y = 1*A + 2*B + 5*C + k.\\nPoint 1: 10 + 10 + 10 + k = 20 => 30 + k = 20 => k = -10.\\nCheck Point 2: 20 + 10 + 10 - 10 = 30. Matches.\\nCheck Point 3: 20 + 0 + 10 - 10 = 20. Matches.\\nCheck Point 4: 20 + 10 + 15 - 10 = 35. Matches.\\n\\nSo the equation is Y = A + 2*B + 5*C - 10.\\n\\nWait, let me double check the Step 4 observation. The prompt says:\\nStep 4 state after: {'A': 20.0, 'B': 5.0, 'C': 3.0, 'Y': 35.0}\\nPrevious state (Step 3 after): {'A': 20.0, 'B': 5.0, 'C': 2.0, 'Y': 30.0}\\nYes, delta C = 1, delta Y = 5. So coefficient of C is 5.\\n\\nSo the equation is Y = A + 2*B + 5*C - 10.\\n\\nI have enough evidence to finish.\",\n  \"step_type\": \"finish\",\n  \"action\": null,\n  \"final_equation"], [26, false, false, false, "parse_error", 3, null, null, 1.0, 0.0, 0.0, 0.0, "model output is not valid JSON: {\n  \"reasoning\": \"Based on the history: Step 0 showed increasing A by 10 increased Y by 10 (slope 1 for A). Step 1 showed increasing B by 5 increased Y by 10 (slope 2 for B). Step 2 showed increasing C by 1 resulted in no change to Y (30 -> 40? Wait, let's re-read Step 2 carefully). \\nRe-evaluating Step 2: State before was A=10, B=10, C=2, Y=30. Action was 'increase C'. State after is A=10, B=10, C=3, Y=40. \\nWait, Y changed from 30 to 40 when C changed from 2 to 3? That's a change of +10. \\nLet's re-calculate the slopes based on the provided history data points:\\n1. Point 0: A=0, B=5, C=2 -> Y=10. (From Step 0 state before)\\n2. Point 1: A=10, B=5, C=2 -> Y=20. (From Step 0 state after). Change: A+10, Y+10. Slope A = 1.\\n3. Point 2: A=10, B=10, C=2 -> Y=30. (From Step 1 state after). Change: B+5, Y+10. Slope B = 10/5 = 2.\\n4. Point 3: A=10, B=10, C=3 -> Y=40. (From Step 2 state after). Change: C+1, Y+10. Slope C = 10/1 = 10.\\n\\nSo the equation seems to be Y = 1*A + 2*B + 10*C.\\nLet's verify with the initial observation in the prompt: A=10, B=10, C=3, Y=40. \\nFormula: 1*10 + 2*10 + 10*3 = 10 + 20 + 30 = 60. \\nBut the prompt says Y=40 for A=10, B=10, C=3. \\nThere is a contradiction between my derivation from the history steps and the current observation provided in the prompt description.\\n\\nLet's re-read the history steps very carefully.\\nStep 0: Before (0, 5, 2) -> Y=10. After (10, 5, 2) -> Y=20. Delta A=10, Delta Y=10. Slope A = 1.\\nStep 1: Before (10, 5, 2) -> Y=20. After (10, 10, 2) -> Y=30. Delta B=5, Delta Y=10. Slope B = 2.\\nStep 2: Before (10, 10, 2) -> Y=30. After (10, 10, 3) -> Y=40. Delta C=1, Delta Y=10. Slope C = 10.\\n\\nEquation derived from history: Y = A + 2B + 10C.\\nCheck Step 2 result: A=10, B=10, C=2 -> Y = 10 + 20 + 20 = 50. But history says Y=30. \\nCheck Step 0 result: A=0, B=5, C=2 -> Y = 0 + 10 + 20 = 30. But history says Y=10.\\n\\nThe history data points do not fit a simple linear sum Y = aA + bB + cC. Let's look at the values again.\\nPoint 0 (Step 0 before): A=0, B=5, C=2, Y=10.\\nPoint 1 (Step 0 after): A=10, B=5, C=2, Y=20.\\nPoint 2 (Step 1 after): A=10, B=10, C=2, Y=30.\\nPoint 3 (Step 2 after): A=10, B=10, C=3, Y=40.\\n\\nLet's try: Y = A + B + C + 4? \\n0+5+2+4 = 11 (No, Y=1"], [27, false, false, false, "parse_error", 0, null, null, 0.0, 0.0, 0.0, 0.0, "model output is not valid JSON: {\n  \"reasoning\": \"I need to find the relationship between A, B, C, and Y. Current values are A=0, B=5, C=2, Y=10. Let's test if Y = A + B + C. 0 + 5 + 2 = 7, which is not 10. Let's try Y = 2*B + C. 2*5 + 2 = 12, not 10. Let's try Y = B + 2*C. 5 + 4 = 9, close but not 10. Let's try Y = A + B + 2*C. 0 + 5 + 4 = 9. Let's try Y = 2*A + B + C. 0 + 5 + 2 = 7. Let's try Y = A + 2*B + C. 0 + 10 + 2 = 12. Let's try Y = B + C + A? No. Maybe Y = 2*B + A + C? 10 + 0 + 2 = 12. What about Y = B + C + A + something? Or maybe Y = 2*B + C - A? 10 + 2 - 0 = 12. Let's try Y = B + 2*C + A? 5 + 4 + 0 = 9. Let's try Y = 2*B + A + C? 10. Let's re-evaluate. A=0, B=5, C=2, Y=10. If I change B to 6, does Y become 12? If Y = 2*B + C, then 2*5+2=12. Wait, 2*5=10, +2=12. But Y is 10. So maybe Y = 2*B? 2*5=10. That fits! Let's check if C or A matter. If Y depends only on B, then changing A or C shouldn't change Y. Let's increase A and see if Y changes. If Y stays 10, then Y might be independent of A and C, or dependent in a way that cancels out. But first, let's test the hypothesis Y = 2*B. If I increase A, and Y stays 10, then A is irrelevant. If I change B, Y should change proportionally. Let's increase A first to test independence.\"\n  \"step_type\": \"action\",\n  \"action\": {\n    \"action_type\": \"increase\",\n    \"variable\": \"A\"\n  },\n  \"final_equation\": null\n}"], [28, false, false, false, "parse_error", 3, null, null, 1.0, 0.0, 0.0, 0.0, "model output is not valid JSON: {\n  \"reasoning\": \"I have tested A (coeff 1), B (coeff 2), and C. From Step 0 (A=0, B=5, C=2, Y=10) and Step 1 (A=10, B=10, C=2, Y=30), I deduced Y = A + 2B. However, in Step 2, I changed C from 2.0 to 1.0 while keeping A=10 and B=10 constant. The state before was Y=30.0, and the state after is Y=20.0. Since C changed by -1 and Y changed by -10, the coefficient for C is 10. Therefore, the equation is Y = A + 2*B + 10*C. I will now verify this equation with the current state: 10 + 2*10 + 10*1 = 10 + 20 + 10 = 40. Wait, the observed Y is 20.0. Let me re-evaluate the coefficient of C. Change in C = -1. Change in Y = -10. Coeff C = 10. Equation: Y = A + 2B + 10C. Check Step 0: 0 + 2*5 + 10*2 = 10 + 20 = 30. But observed Y was 10.0. Contradiction. Let's re-read the history carefully.\\n\\nRe-evaluating Step 0: State before: A=0, B=5, C=2, Y=10. State after: A=10, B=5, C=2, Y=20. Delta A=10, Delta Y=10. Coeff A = 1.\\nRe-evaluating Step 1: State before: A=10, B=5, C=2, Y=20. State after: A=10, B=10, C=2, Y=30. Delta B=5, Delta Y=10. Coeff B = 2.\\nRe-evaluating Step 2: State before: A=10, B=10, C=2, Y=30. State after: A=10, B=10, C=1, Y=20. Delta C = -1. Delta Y = -10. Coeff C = 10.\\n\\nLet's check the consistency of Y = A + 2B + 10C.\\nStep 0 After: A=10, B=5, C=2. Y = 10 + 2*5 + 10*2 = 10 + 10 + 20 = 40. Observed Y=20. Mismatch.\\nStep 1 After: A=10, B=10, C=2. Y = 10 + 2*10 + 10*2 = 10 + 20 + 20 = 50. Observed Y=30. Mismatch.\\nStep 2 After: A=10, B=10, C=1. Y = 10 + 2*10 + 10*1 = 10 + 20 + 10 = 40. Observed Y=20. Mismatch.\\n\\nThe relationship must be different. Let's look at the deltas again.\\nStep 0: A: 0->10 (+10), Y: 10->20 (+10). Coeff A = 1.\\nStep 1: B: 5->10 (+5), Y: 20->30 (+10). Coeff B = 2.\\nStep 2: C: 2->1 (-1), Y: 30->20 (-10). Coeff C = 10.\\n\\nWait, maybe the base values matter? Or maybe my calculation of the equation is wrong because the initial state (Step 0 Before) was A=0, B=5, C=2, Y=10. If Y = A + 2B + kC, then 10 = 0 + 2*5 + k*2 => 10 = 10 + 2k => k=0. So Y = A + 2B. Let's check this against Step 1 After: A=10, B=10, C=2. Y = 10 + 2*10 = 30. Matches observed Y"], [29, false, false, false, "parse_error", 3, null, null, 1.0, 0.0, 0.0, 0.0, "model output is not valid JSON: {\n  \"reasoning\": \"Based on the observations: 1) When A increased by 10 (0->10) with B=5, C=2, Y increased by 10 (10->20). This implies coefficient for A is 1. 2) When B increased by 5 (5->10) with A=10, C=2, Y increased by 10 (20->30). This implies coefficient for B is 2 (since 5 * 2 = 10). 3) When C increased by 1 (2->3) with A=10, B=10, Y increased by 10 (30->40). This implies coefficient for C is 10 (since 1 * 10 = 10). Combining these, Y = 1*A + 2*B + 10*C. Let's verify with current state: 10 + 2*10 + 10*3 = 10 + 20 + 30 = 60. Wait, current Y is 40. My calculation for step 2 result was Y=40 with C=3. Let's re-evaluate. Step 0: A=0, B=5, C=2, Y=10. Step 1: A=10, B=5, C=2, Y=20. Delta A=10, Delta Y=10 -> coeff A = 1. Step 1: A=10, B=5, C=2, Y=20. Step 2: A=10, B=10, C=2, Y=30. Delta B=5, Delta Y=10 -> coeff B = 2. Step 2: A=10, B=10, C=2, Y=30. Step 3 (current): A=10, B=10, C=3, Y=40. Delta C=1, Delta Y=10 -> coeff C = 10. Equation: Y = A + 2B + 10C. Check current state: 10 + 20 + 30 = 60. But Y is 40. There is a contradiction. Let's re-read the history carefully. Step 0 state: A=0, B=5, C=2, Y=10. Step 1 state: A=10, B=5, C=2, Y=20. Change A: +10, Change Y: +10. Slope A = 1. Step 1 state: A=10, B=5, C=2, Y=20. Step 2 state: A=10, B=10, C=2, Y=30. Change B: +5, Change Y: +10. Slope B = 2. Step 2 state: A=10, B=10, C=2, Y=30. Step 3 state: A=10, B=10, C=3, Y=40. Change C: +1, Change Y: +10. Slope C = 10. Equation Y = A + 2B + 10C. Check Step 0: 0 + 2*5 + 10*2 = 0 + 10 + 20 = 30. But Y=10. Something is wrong. Maybe the equation is Y = A + B + C? Step 0: 0+5+2=7 != 10. Maybe Y = 2A + 2B + 2C? Step 0: 0+10+4=14 != 10. Let's re-examine the deltas. Step 0 to 1: A 0->10 (+10), Y 10->20 (+10). Ratio 1. Step 1 to 2: B 5->10 (+5), Y 20->30 (+10). Ratio 2. Step 2 to 3: C 2->3 (+1), Y 30->40 (+10). Ratio 10. Is it possible the equation is Y = A + B + 10*C? Step 0: 0+5+20=25 != 10. Is it possible the equation is Y = A + 2B + C? Step 0: 0+10+2=12 != 10. Is it possible the equation is Y = A + B + C + something?"]], "log_mode": "IMMUTABLE", "ncols": 13, "nrows": 30}