[
  {
    "step_id": 0,
    "step_type": "action",
    "reasoning": "Given that the total distance is the sum of the three segments, we can start by investigating if changing one segment affects the total distance. Let's increase d1 to see if it changes the total distance.",
    "parsed_action": {
      "action_type": "increase",
      "variable": "d1"
    },
    "final_equation": null,
    "done": false
  },
  {
    "step_id": 1,
    "step_type": "action",
    "reasoning": "Since increasing d1 from 10.0 to 20.0 doubled the total distance, it seems that the total distance is linearly related to d1. Let's check if this linear relationship holds for other segments as well.",
    "parsed_action": {
      "action_type": "increase",
      "variable": "d2"
    },
    "final_equation": null,
    "done": false
  }
]