[
  {
    "step_id": 0,
    "step_type": "action",
    "reasoning": "Start by changing one variable to observe its effect on mass.",
    "parsed_action": {
      "action_type": "increase",
      "variable": "density"
    },
    "final_equation": null,
    "done": false
  },
  {
    "step_id": 1,
    "step_type": "action",
    "reasoning": "Start by changing one variable to observe its effect on mass.",
    "parsed_action": {
      "action_type": "increase",
      "variable": "volume"
    },
    "final_equation": null,
    "done": false
  },
  {
    "step_id": 2,
    "step_type": "action",
    "reasoning": "Change volume to observe its effect on mass.",
    "parsed_action": {
      "action_type": "decrease volume",
      "variable": "volume"
    },
    "final_equation": null,
    "done": false
  },
  {
    "step_id": 3,
    "step_type": "action",
    "reasoning": "Changing volume to observe its effect on mass, and then decrease it to see if the effect is reversible.",
    "parsed_action": {
      "action_type": "decrease volume",
      "variable": "volume"
    },
    "final_equation": null,
    "done": false
  },
  {
    "step_id": 4,
    "step_type": "action",
    "reasoning": "Try to understand the relationship between density and mass.",
    "parsed_action": {
      "action_type": "decrease density",
      "variable": "density"
    },
    "final_equation": null,
    "done": false
  },
  {
    "step_id": 5,
    "step_type": "action",
    "reasoning": "Increase density to see its effect on mass.",
    "parsed_action": {
      "action_type": "increase",
      "variable": "k"
    },
    "final_equation": null,
    "done": false
  },
  {
    "step_id": 6,
    "step_type": "action",
    "reasoning": "Since changing k has a direct effect on mass, and density and volume are constant, I will change k to see if it affects mass.",
    "parsed_action": {
      "action_type": "decrease k",
      "variable": "k"
    },
    "final_equation": null,
    "done": false
  },
  {
    "step_id": 7,
    "step_type": "action",
    "reasoning": "Change k to see if it affects mass, given that density and volume are constant.",
    "parsed_action": {
      "action_type": "increase",
      "variable": "k"
    },
    "final_equation": null,
    "done": false
  },
  {
    "step_id": 8,
    "step_type": "action",
    "reasoning": "Increasing k and observing the effect on mass, since it directly affects mass.",
    "parsed_action": {
      "action_type": "increase k",
      "variable": "k"
    },
    "final_equation": null,
    "done": false
  },
  {
    "step_id": 9,
    "step_type": "action",
    "reasoning": "Increasing k to observe its effect on mass.",
    "parsed_action": {
      "action_type": "increase k",
      "variable": "k"
    },
    "final_equation": null,
    "done": false
  },
  {
    "step_id": 10,
    "step_type": "action",
    "reasoning": "Increase volume to see its effect on mass.",
    "parsed_action": {
      "action_type": "increase volume",
      "variable": "volume"
    },
    "final_equation": null,
    "done": false
  },
  {
    "step_id": 11,
    "step_type": "action",
    "reasoning": "Since k has a direct effect on mass, and density and volume are constant, I will try to understand its relationship with mass.",
    "parsed_action": {
      "action_type": "decrease k",
      "variable": "k"
    },
    "final_equation": null,
    "done": false
  },
  {
    "step_id": 12,
    "step_type": "action",
    "reasoning": "k is directly proportional to mass, as changing k always results in a direct change in mass.",
    "parsed_action": {
      "action_type": "decrease k",
      "variable": "k"
    },
    "final_equation": null,
    "done": false
  },
  {
    "step_id": 13,
    "step_type": "action",
    "reasoning": "k is directly proportional to mass, as changing k always results in a direct change in mass, and volume and density are constant.",
    "parsed_action": {
      "action_type": "decrease k",
      "variable": "k"
    },
    "final_equation": null,
    "done": false
  },
  {
    "step_id": 14,
    "step_type": "finish",
    "reasoning": "k is directly proportional to mass, and density and volume are constant, so the equation is mass = k * volume * density.",
    "parsed_action": null,
    "final_equation": "mass = k * volume * density",
    "done": true
  }
]