[
  {
    "step_id": 0,
    "step_type": "action",
    "reasoning": "Initial observation shows that Y = 20.0, A = 2.0, and B = 10.0. No clear relationship is evident between Y and A or B. Increasing or decreasing A or B may reveal a relationship.",
    "parsed_action": {
      "action_type": "increase",
      "variable": "A"
    },
    "final_equation": null,
    "done": false
  },
  {
    "step_id": 1,
    "step_type": "action",
    "reasoning": "Y has doubled when A increased from 2.0 to 3.0 while B remained constant. This suggests a possible linear relationship between Y and A. Let's keep A constant and decrease B to see if Y changes accordingly.",
    "parsed_action": {
      "action_type": "decrease",
      "variable": "B"
    },
    "final_equation": null,
    "done": false
  },
  {
    "step_id": 2,
    "step_type": "action",
    "reasoning": "Y is now 0.0 when B is 0.0 and A is 3.0. This indicates that Y may be a function of A with B having no influence. Let's increase A again to confirm.",
    "parsed_action": {
      "action_type": "increase",
      "variable": "A"
    },
    "final_equation": null,
    "done": false
  }
]