[
  {
    "step_id": 0,
    "step_type": "action",
    "reasoning": "Initial observation suggests a linear relationship between x, v, t, and x0. Increasing t might help confirm if x is indeed a function of velocity and time.",
    "parsed_action": {
      "action_type": "increase",
      "variable": "t"
    },
    "final_equation": null,
    "done": false
  },
  {
    "step_id": 1,
    "step_type": "action",
    "reasoning": "Increasing t from 2.0 to 3.0 resulted in x increasing from 10.0 to 15.0, suggesting a direct relationship between x and t. The increase in x is consistent with a constant velocity scenario (x = x0 + vt). To confirm, I will now increase v.",
    "parsed_action": {
      "action_type": "increase",
      "variable": "v"
    },
    "final_equation": null,
    "done": false
  },
  {
    "step_id": 2,
    "step_type": "finish",
    "reasoning": "The increase in velocity from 5.0 to 10.0 while keeping t constant at 3.0 resulted in x increasing from 15.0 to 30.0, which supports the equation x = x0 + vt. No further action is needed to confirm this linear relationship.",
    "parsed_action": null,
    "final_equation": "x = x0 + v * t",
    "done": true
  }
]