[
  {
    "step_id": 0,
    "step_type": "action",
    "reasoning": "I will increase rho to see how m changes relative to the other variables.",
    "parsed_action": {
      "action_type": "increase",
      "variable": "rho"
    },
    "final_equation": null,
    "done": false
  },
  {
    "step_id": 1,
    "step_type": "action",
    "reasoning": "I have observed that increasing rho from 2.0 to 3.0 caused m to increase from 60.0 to 90.0. This suggests a linear relationship where m = c * rho. The ratio 90/3 = 30 and 60/2 = 30, so the constant c appears to be 30. Now I need to check if V or k affect m. I will increase V to see if m changes.",
    "parsed_action": {
      "action_type": "increase",
      "variable": "V"
    },
    "final_equation": null,
    "done": false
  },
  {
    "step_id": 2,
    "step_type": "action",
    "reasoning": "I have observed that when rho doubled (2.0 to 4.0), m quadrupled (60.0 to 240.0). This suggests m is proportional to rho squared. Also, when V doubled (10.0 to 20.0) while rho and k stayed constant, m doubled (60.0 to 120.0). This suggests m is proportional to V. Since rho and V are independent factors, the relationship is likely m = c * rho^2 * V. Let's test this by increasing k to see if it affects m. If m depends on k, the constant c will change or the formula will include k. If m stays constant, then k is not in the equation.",
    "parsed_action": {
      "action_type": "increase",
      "variable": "k"
    },
    "final_equation": null,
    "done": false
  },
  {
    "step_id": 3,
    "step_type": "finish",
    "reasoning": "I have observed that increasing rho from 2.0 to 3.0 caused m to increase from 60.0 to 90.0 (factor of 1.5 -> factor of 1.5, wait, 60*1.5=90). Then increasing rho to 4.0 (in step 0 history says 2->4, m 60->240, factor 2->4, squared). Increasing V from 10 to 20 doubled m from 90 to 180. Increasing k from 3 to 4 did not change m (180 to 180? No, step 2 says m went from 180 to 240? Wait, let's re-read Step 2 carefully. Step 1 ended with m=180. Step 2 increased k from 3 to 4, and m went from 180 to 240? That contradicts the hypothesis that k is not involved. Let me re-examine the data points provided in the history.\n\nData points:\n1. rho=2, V=10, k=3 -> m=60\n2. rho=3, V=10, k=3 -> m=90 (rho x1.5, m x1.5)\n3. rho=3, V=20, k=3 -> m=180 (V x2, m x2)\n4. rho=3, V=20, k=4 -> m=240 (k x1.33, m x1.33)\n\nWait, looking at Step 2 history again: 'state before: ... m: 180.0', 'state after: ... m: 240.0'. This implies m changed when k changed. If m=180 at k=3 and m=240 at k=4, then m depends on k. The ratio of m is 240/180 = 4/3. The ratio of k is 4/3. So m is proportional to k.\n\nLet's re-evaluate the relationship.\nFrom point 1 (2, 10, 3) to point 2 (3, 10, 3): rho 2->3 (x1.5), m 60->90 (x1.5). So m ~ rho.\nFrom point 2 (3, 10, 3) to point 3 (3, 20, 3): V 10->20 (x2), m 90->180 (x2). So m ~ V.\nFrom point 3 (3, 20, 3) to point 4 (3, 20, 4): k 3->4 (x1.33), m 180->240 (x1.33). So m ~ k.\n\nSo m is directly proportional to rho, V, and k. m = c * rho * V * k.\nLet's find c.\nUsing point 1: 60 = c * 2 * 10 * 3 => 60 = 60c => c = 1.\nUsing point 2: 90 = 1 * 3 * 10 * 3 => 90 = 90. Correct.\nUsing point 3: 180 = 1 * 3 * 20 * 3 => 180 = 180. Correct.\nUsing point 4: 240 = 1 * 3 * 20 * 4 => 240 = 240. Correct.\n\nThe equation is m = rho * V * k. I have sufficient evidence. I will finish.",
    "parsed_action": null,
    "final_equation": "m = rho * V * k",
    "done": true
  }
]