[
  {
    "step_id": 0,
    "step_type": "action",
    "reasoning": "I start with A=10, B=5, Y=15. I will increase A by 1 to see how Y changes. If Y increases by the same amount as A, it might be linear (Y = A + B). If Y stays constant, it might be independent of A.",
    "parsed_action": {
      "action_type": "increase",
      "variable": "A"
    },
    "final_equation": null,
    "done": false
  },
  {
    "step_id": 1,
    "step_type": "action",
    "reasoning": "I observed that increasing A from 10 to 20 (delta A = +10) caused Y to increase from 15 to 25 (delta Y = +10), while B remained constant at 5. This suggests a linear relationship where Y depends on A and B. The change in Y equals the change in A, implying a coefficient of 1 for A. Testing the hypothesis Y = A + B: 10 + 5 = 15 (matches start), 20 + 5 = 25 (matches current). I need to verify if the coefficient for A is exactly 1 or if there's an offset, and confirm B's role. Let's increase B to see if Y changes proportionally, while keeping A constant to isolate B's effect.",
    "parsed_action": {
      "action_type": "increase",
      "variable": "B"
    },
    "final_equation": null,
    "done": false
  }
]