[
  {
    "step_id": 0,
    "step_type": "action",
    "reasoning": "Start with a basic action to see how the environment responds.",
    "parsed_action": {
      "action_type": "increase",
      "variable": "x0"
    },
    "final_equation": null,
    "done": false
  },
  {
    "step_id": 1,
    "step_type": "action",
    "reasoning": "Start with a basic action to see how the environment responds.",
    "parsed_action": {
      "action_type": "increase",
      "variable": "x0"
    },
    "final_equation": null,
    "done": false
  },
  {
    "step_id": 2,
    "step_type": "action",
    "reasoning": "Increase x0 to see its effect on the environment.",
    "parsed_action": {
      "action_type": "increase",
      "variable": "x0"
    },
    "final_equation": null,
    "done": false
  },
  {
    "step_id": 3,
    "step_type": "action",
    "reasoning": "Increase v to see its effect on the environment.",
    "parsed_action": {
      "action_type": "increase",
      "variable": "v"
    },
    "final_equation": null,
    "done": false
  },
  {
    "step_id": 4,
    "step_type": "action",
    "reasoning": "Increase t to see its effect on the environment.",
    "parsed_action": {
      "action_type": "increase",
      "variable": "t"
    },
    "final_equation": null,
    "done": false
  },
  {
    "step_id": 5,
    "step_type": "action",
    "reasoning": "Increase x0 to see its effect on the environment.",
    "parsed_action": {
      "action_type": "increase",
      "variable": "t"
    },
    "final_equation": null,
    "done": false
  },
  {
    "step_id": 6,
    "step_type": "action",
    "reasoning": "Increase x to see its effect on the environment.",
    "parsed_action": {
      "action_type": "increase",
      "variable": "x"
    },
    "final_equation": null,
    "done": false
  },
  {
    "step_id": 7,
    "step_type": "action",
    "reasoning": "Try to relate x with x0 and v by changing x0 and v",
    "parsed_action": {
      "action_type": "decrease v",
      "variable": "v"
    },
    "final_equation": null,
    "done": false
  },
  {
    "step_id": 8,
    "step_type": "action",
    "reasoning": "Try to relate x with x0 and v by changing x0 and v",
    "parsed_action": {
      "action_type": "decrease v",
      "variable": "v"
    },
    "final_equation": null,
    "done": false
  },
  {
    "step_id": 9,
    "step_type": "action",
    "reasoning": "Try to relate x with x0 and v by changing v",
    "parsed_action": {
      "action_type": "increase v",
      "variable": "v"
    },
    "final_equation": null,
    "done": false
  },
  {
    "step_id": 10,
    "step_type": "action",
    "reasoning": "Try to relate x with x0 and v by changing v",
    "parsed_action": {
      "action_type": "increase v",
      "variable": "v"
    },
    "final_equation": null,
    "done": false
  },
  {
    "step_id": 11,
    "step_type": "action",
    "reasoning": "Try to relate x with x0 and v by changing x0",
    "parsed_action": {
      "action_type": "increase x0",
      "variable": "x0"
    },
    "final_equation": null,
    "done": false
  },
  {
    "step_id": 12,
    "step_type": "action",
    "reasoning": "Try to relate x with x0 and v by changing x0 and v",
    "parsed_action": {
      "action_type": "decrease v",
      "variable": "v"
    },
    "final_equation": null,
    "done": false
  },
  {
    "step_id": 13,
    "step_type": "action",
    "reasoning": "Try to relate x with x0 and v by changing x0 and v",
    "parsed_action": {
      "action_type": "increase x0",
      "variable": "x0"
    },
    "final_equation": null,
    "done": false
  },
  {
    "step_id": 14,
    "step_type": "action",
    "reasoning": "Since the current state of x is not changing despite changing x0, v, and t, I will try to change x0 and v to see if x is affected.",
    "parsed_action": {
      "action_type": "increase v",
      "variable": "v"
    },
    "final_equation": null,
    "done": false
  },
  {
    "step_id": 15,
    "step_type": "action",
    "reasoning": "Try to relate x with x0 and v by changing x0 and v",
    "parsed_action": {
      "action_type": "increase x0",
      "variable": "x0"
    },
    "final_equation": null,
    "done": false
  },
  {
    "step_id": 16,
    "step_type": "action",
    "reasoning": "Try to relate x with x0 and v by changing v",
    "parsed_action": {
      "action_type": "decrease v",
      "variable": "v"
    },
    "final_equation": null,
    "done": false
  },
  {
    "step_id": 17,
    "step_type": "action",
    "reasoning": "Try to increase x0 to see its effect on the environment.",
    "parsed_action": {
      "action_type": "increase",
      "variable": "x0"
    },
    "final_equation": null,
    "done": false
  },
  {
    "step_id": 18,
    "step_type": "action",
    "reasoning": "From step 17, increasing x0 from 30 to 40 results in x increasing from 70 to 80, so it seems x is directly proportional to x0.",
    "parsed_action": {
      "action_type": "increase",
      "variable": "t"
    },
    "final_equation": null,
    "done": false
  },
  {
    "step_id": 19,
    "step_type": "action",
    "reasoning": "Try to increase x0 to see its effect on the environment.",
    "parsed_action": {
      "action_type": "increase",
      "variable": "x0"
    },
    "final_equation": null,
    "done": false
  },
  {
    "step_id": 20,
    "step_type": "action",
    "reasoning": "Try to relate x with x0 and v by changing x0",
    "parsed_action": {
      "action_type": "increase x0",
      "variable": "x0"
    },
    "final_equation": null,
    "done": false
  },
  {
    "step_id": 21,
    "step_type": "action",
    "reasoning": "Try to relate x with x0 by changing x0",
    "parsed_action": {
      "action_type": "increase",
      "variable": "x0"
    },
    "final_equation": null,
    "done": false
  },
  {
    "step_id": 22,
    "step_type": "action",
    "reasoning": "Try to relate x with x0 by changing x0",
    "parsed_action": {
      "action_type": "increase",
      "variable": "x0"
    },
    "final_equation": null,
    "done": false
  },
  {
    "step_id": 23,
    "step_type": "action",
    "reasoning": "Since increasing x0 results in a direct proportionality with x, I will try to determine the relationship between x0 and x.",
    "parsed_action": {
      "action_type": "increase",
      "variable": "x0"
    },
    "final_equation": null,
    "done": false
  },
  {
    "step_id": 24,
    "step_type": "action",
    "reasoning": "Try to determine the relationship between x0 and x by increasing x0",
    "parsed_action": {
      "action_type": "increase",
      "variable": "x0"
    },
    "final_equation": null,
    "done": false
  },
  {
    "step_id": 25,
    "step_type": "action",
    "reasoning": "Try to increase x0 to see its effect on the environment.",
    "parsed_action": {
      "action_type": "increase x0",
      "variable": "x0"
    },
    "final_equation": null,
    "done": false
  },
  {
    "step_id": 26,
    "step_type": "action",
    "reasoning": "x is directly proportional to x0",
    "parsed_action": {
      "action_type": "increase",
      "variable": "x0"
    },
    "final_equation": null,
    "done": false
  },
  {
    "step_id": 27,
    "step_type": "action",
    "reasoning": "Try to relate x with x0 and v by changing x0 and v",
    "parsed_action": {
      "action_type": "increase v",
      "variable": "v"
    },
    "final_equation": null,
    "done": false
  },
  {
    "step_id": 28,
    "step_type": "action",
    "reasoning": "x is directly proportional to x0, and increasing x0 results in a direct proportionality with x.",
    "parsed_action": {
      "action_type": "increase",
      "variable": "x0"
    },
    "final_equation": null,
    "done": false
  },
  {
    "step_id": 29,
    "step_type": "finish",
    "reasoning": "x is directly proportional to x0, and increasing x0 results in a direct proportionality with x.",
    "parsed_action": null,
    "final_equation": "x = x0",
    "done": true
  }
]